Workbook

Sheet Sheet2
A3: Row Labels
A4: 1
A5: 2
A6: 50000
A7: 50000 investement
A8: Details Share once again
A9: Month End
A10: Rejected
A11: RejectedR6
A12: vadodra Hr no / 3 NR
A13: Will Come
A14: Will decide and Call
A15: Will Take Decious / Rejected
A16: will take time
A17: / fever once he ias ok
A18: / Pospond
... A215: YashPal no Given / Will Take time
A216: 46028
A217: (blank)
A218: Grand Total

Sheet Sheet3
A3: Row Labels
A4: Deal
A5: Deal
A6: Follow up
A7: Rejected
A8: Rejected
A9: Ringing
A10: (blank)
A11: Grand Total

Sheet Sheet13
A3: Row Labels
A4: Assam | B4: East
A5: Bihar | B5: East
A6: Bihar
A7: Chattisgarh | B7: Central
A8: Delhi | B8: North
A9: Goa | B9: West
A10: Gujarat | B10: West
A11: Gujarat
A12: Haryana | B12: North
A13: haryana
A14: jharkhand | B14: East
A15: Madhya Pradesh | B15: Central
A16: Maharashtra | B16: West
A17: Manipur | B17: East
A18: Meghalaya | B18: East
A19: Odisha | B19: East
A20: Punjab | B20: North
A21: Punjab
A22: Rajasthan | B22: West
A23: Uttar Pradesh | B23: North
A24: Uttar Pradesh
A25: Uttrakhand | B25: North
A26: West Bengal | B26: East
A27: (blank)
A28: Grand Total

Sheet Sheet14
A1: Assam | B1: East
A2: Bihar | B2: East
A3: Chattisgarh | B3: Central
A4: Delhi | B4: North
A5: Goa | B5: West
A6: Gujarat | B6: West
A7: Haryana | B7: North
A8: jharkhand | B8: East
A9: Madhya Pradesh | B9: Central
A10: Maharashtra | B10: West
A11: Manipur | B11: East
A12: Meghalaya | B12: East
... A18: West Bengal | B18: East

Sheet Dashboard
A1: Franchise Sales Performance Dashboard
A3: Lead Conversion • Revenue • Sales Performance Analytics
A5: 📞Total Leads | E5: Conversion Rate % | I5: Revenue Generated
A6: =KPI_Databse!B1 -> 1778 | E6: =KPI_Databse!B3 -> 0.025309336 | I6: =KPI_Databse!B4 -> 6198000
A11: Pipeline Value | E11: Lost Opportunity | I11: Avg Days To Closure
A12: =KPI_Databse!B5 -> 69576000 | E12: =KPI_Databse!B6 -> 119264000 | I12: =KPI_Databse!B7 -> 13

Sheet Cleaned_CRM_Data
A1: Lead ID | B1: Date | C1: Campaign | D1: Clean_Campaign | E1: Name | F1: city | G1: State | H1: Remark | I1: Franchise Package Amount | J1: investment Amount | K1: Clean_Remark | L1: Standard Status | M1: Closing Date | N1: Days To Closure | O1: Pacakge Category | P1: Lead Month | Q1: Lead Quarter | R1: Zone
A2: ="EOS"&TEXT(ROW()-1,"0000") -> EOS0001 | B2: 45817 | C2: FB | D2: =TRIM(CLEAN(SUBSTITUTE(C2,CHAR(160),""))) -> FB | E2: Rathod Kuldipsinh | F2: Kodinar | G2: Gujarat | H2: Rejected | I2: 130000 | J2: 107000 | K2: =TRIM(Cleaned_CRM_Data!H2) -> Rejected | L2: =IFERROR(VLOOKUP(K2, Status_Mapping!A:B, 2,), "Not Found") -> Rejected | N2: =IF(M2="","",M2-B2) | O2: =IF(OR(I2=108000,I2=130000),"Starter",IF(I2=177000,"Growth","Premium")) -> Starter | P2: =TEXT(B2, "mmmm") -> June | Q2: ="Q"&ROUNDUP(MONTH(B2)/3,0) -> Q2 | R2: =IFERROR(VLOOKUP(TRIM(CLEAN(G2)),Sheet14!$A$2:$B$19,2,FALSE),"Not Mapped") -> West
A3: ="EOS"&TEXT(ROW()-1,"0000") -> EOS0002 | B3: 45817 | C3: FB | D3: =TRIM(CLEAN(SUBSTITUTE(C3,CHAR(160),""))) -> FB | E3: Kiran Lashkari | F3: Bhavnagar | G3: Gujarat | H3: Rejected | I3: 108000 | J3: 107001 | K3: =TRIM(Cleaned_CRM_Data!H3) -> Rejected | L3: =IFERROR(VLOOKUP(K3, Status_Mapping!A:B, 2,), "Not Found") -> Rejected | N3: =IF(M3="","",M3-B3) | O3: =IF(OR(I3=108000,I3=130000),"Starter",IF(I3=177000,"Growth","Premium")) -> Starter | P3: =TEXT(B3, "mmmm") -> June | Q3: ="Q"&ROUNDUP(MONTH(B3)/3,0) -> Q2 | R3: =IFERROR(VLOOKUP(TRIM(CLEAN(G3)),Sheet14!$A$2:$B$19,2,FALSE),"Not Mapped") -> West
A4: ="EOS"&TEXT(ROW()-1,"0000") -> EOS0003 | B4: 45817 | C4: FB | D4: =TRIM(CLEAN(SUBSTITUTE(C4,CHAR(160),""))) -> FB | E4: Abhay Naik | F4: Bardoli | G4: Gujarat | H4: Rejected | I4: 108000 | J4: 107002 | K4: =TRIM(Cleaned_CRM_Data!H4) -> Rejected | L4: =IFERROR(VLOOKUP(K4, Status_Mapping!A:B, 2,), "Not Found") -> Rejected | N4: =IF(M4="","",M4-B4) | O4: =IF(OR(I4=108000,I4=130000),"Starter",IF(I4=177000,"Growth","Premium")) -> Starter | P4: =TEXT(B4, "mmmm") -> June | Q4: ="Q"&ROUNDUP(MONTH(B4)/3,0) -> Q2 | R4: =IFERROR(VLOOKUP(TRIM(CLEAN(G4)),Sheet14!$A$2:$B$19,2,FALSE),"Not Mapped") -> West
A5: ="EOS"&TEXT(ROW()-1,"0000") -> EOS0004 | B5: 45817 | C5: FB | D5: =TRIM(CLEAN(SUBSTITUTE(C5,CHAR(160),""))) -> FB | E5: Kunalpatel | F5: Ahmedabad | G5: Gujarat | H5: Rejected | I5: 177000 | J5: 107003 | K5: =TRIM(Cleaned_CRM_Data!H5) -> Rejected | L5: =IFERROR(VLOOKUP(K5, Status_Mapping!A:B, 2,), "Not Found") -> Rejected | N5: =IF(M5="","",M5-B5) | O5: =IF(OR(I5=108000,I5=130000),"Starter",IF(I5=177000,"Growth","Premium")) -> Growth | P5: =TEXT(B5, "mmmm") -> June | Q5: ="Q"&ROUNDUP(MONTH(B5)/3,0) -> Q2 | R5: =IFERROR(VLOOKUP(TRIM(CLEAN(G5)),Sheet14!$A$2:$B$19,2,FALSE),"Not Mapped") -> West
A6: ="EOS"&TEXT(ROW()-1,"0000") -> EOS0005 | B6: 45817 | C6: FB | D6: =TRIM(CLEAN(SUBSTITUTE(C6,CHAR(160),""))) -> FB | E6: Kartik Kesarwani | F6: Allahabad | G6: Uttar Pradesh | H6: Rejected | I6: 177000 | J6: 107004 | K6: =TRIM(Cleaned_CRM_Data!H6) -> Rejected | L6: =IFERROR(VLOOKUP(K6, Status_Mapping!A:B, 2,), "Not Found") -> Rejected | N6: =IF(M6="","",M6-B6) | O6: =IF(OR(I6=108000,I6=130000),"Starter",IF(I6=177000,"Growth","Premium")) -> Growth | P6: =TEXT(B6, "mmmm") -> June | Q6: ="Q"&ROUNDUP(MONTH(B6)/3,0) -> Q2 | R6: =IFERROR(VLOOKUP(TRIM(CLEAN(G6)),Sheet14!$A$2:$B$19,2,FALSE),"Not Mapped") -> North
A7: ="EOS"&TEXT(ROW()-1,"0000") -> EOS0006 | B7: 45817 | C7: FB | D7: =TRIM(CLEAN(SUBSTITUTE(C7,CHAR(160),""))) -> FB | E7: Golu_Dwivedi | F7: Gonda | G7: Uttar Pradesh | H7: Rejected | I7: 308000 | J7: 107005 | K7: =TRIM(Cleaned_CRM_Data!H7) -> Rejected | L7: =IFERROR(VLOOKUP(K7, Status_Mapping!A:B, 2,), "Not Found") -> Rejected | N7: =IF(M7="","",M7-B7) | O7: =IF(OR(I7=108000,I7=130000),"Starter",IF(I7=177000,"Growth","Premium")) -> Premium | P7: =TEXT(B7, "mmmm") -> June | Q7: ="Q"&ROUNDUP(MONTH(B7)/3,0) -> Q2 | R7: =IFERROR(VLOOKUP(TRIM(CLEAN(G7)),Sheet14!$A$2:$B$19,2,FALSE),"Not Mapped") -> North
A8: ="EOS"&TEXT(ROW()-1,"0000") -> EOS0007 | B8: 45817 | C8: FB | D8: =TRIM(CLEAN(SUBSTITUTE(C8,CHAR(160),""))) -> FB | E8: સહજાનંદી સિંહ ધુ્વિક પટેલ | F8: Padra | G8: Gujarat | H8: Rejected | I8: 108000 | J8: 107006 | K8: =TRIM(Cleaned_CRM_Data!H8) -> Rejected | L8: =IFERROR(VLOOKUP(K8, Status_Mapping!A:B, 2,), "Not Found") -> Rejected | N8: =IF(M8="","",M8-B8) | O8: =IF(OR(I8=108000,I8=130000),"Starter",IF(I8=177000,"Growth","Premium")) -> Starter | P8: =TEXT(B8, "mmmm") -> June | Q8: ="Q"&ROUNDUP(MONTH(B8)/3,0) -> Q2 | R8: =IFERROR(VLOOKUP(TRIM(CLEAN(G8)),Sheet14!$A$2:$B$19,2,FALSE),"Not Mapped") -> West
A9: ="EOS"&TEXT(ROW()-1,"0000") -> EOS0008 | B9: 45817 | C9: FB | D9: =TRIM(CLEAN(SUBSTITUTE(C9,CHAR(160),""))) -> FB | E9: Het Thacker | F9: Bhuj | G9: Gujarat | H9: Rejected | I9: 130000 | J9: 107007 | K9: =TRIM(Cleaned_CRM_Data!H9) -> Rejected | L9: =IFERROR(VLOOKUP(K9, Status_Mapping!A:B, 2,), "Not Found") -> Rejected | N9: =IF(M9="","",M9-B9) | O9: =IF(OR(I9=108000,I9=130000),"Starter",IF(I9=177000,"Growth","Premium")) -> Starter | P9: =TEXT(B9, "mmmm") -> June | Q9: ="Q"&ROUNDUP(MONTH(B9)/3,0) -> Q2 | R9: =IFERROR(VLOOKUP(TRIM(CLEAN(G9)),Sheet14!$A$2:$B$19,2,FALSE),"Not Mapped") -> West
A10: ="EOS"&TEXT(ROW()-1,"0000") -> EOS0009 | B10: 45817 | C10: FB | D10: =TRIM(CLEAN(SUBSTITUTE(C10,CHAR(160),""))) -> FB | E10: Chintan Patel | F10: Ahmedabad | G10: Gujarat | H10: Rejected | I10: 108000 | J10: 107008 | K10: =TRIM(Cleaned_CRM_Data!H10) -> Rejected | L10: =IFERROR(VLOOKUP(K10, Status_Mapping!A:B, 2,), "Not Found") -> Rejected | N10: =IF(M10="","",M10-B10) | O10: =IF(OR(I10=108000,I10=130000),"Starter",IF(I10=177000,"Growth","Premium")) -> Starter | P10: =TEXT(B10, "mmmm") -> June | Q10: ="Q"&ROUNDUP(MONTH(B10)/3,0) -> Q2 | R10: =IFERROR(VLOOKUP(TRIM(CLEAN(G10)),Sheet14!$A$2:$B$19,2,FALSE),"Not Mapped") -> West
A11: ="EOS"&TEXT(ROW()-1,"0000") -> EOS0010 | B11: 45817 | C11: FB | D11: =TRIM(CLEAN(SUBSTITUTE(C11,CHAR(160),""))) -> FB | E11: Rohit | F11: Baroda | G11: Gujarat | H11: Rejected | I11: 130000 | J11: 107009 | K11: =TRIM(Cleaned_CRM_Data!H11) -> Rejected | L11: =IFERROR(VLOOKUP(K11, Status_Mapping!A:B, 2,), "Not Found") -> Rejected | N11: =IF(M11="","",M11-B11) | O11: =IF(OR(I11=108000,I11=130000),"Starter",IF(I11=177000,"Growth","Premium")) -> Starter | P11: =TEXT(B11, "mmmm") -> June | Q11: ="Q"&ROUNDUP(MONTH(B11)/3,0) -> Q2 | R11: =IFERROR(VLOOKUP(TRIM(CLEAN(G11)),Sheet14!$A$2:$B$19,2,FALSE),"Not Mapped") -> West
A12: ="EOS"&TEXT(ROW()-1,"0000") -> EOS0011 | B12: 45817 | C12: FB | D12: =TRIM(CLEAN(SUBSTITUTE(C12,CHAR(160),""))) -> FB | E12: Balvantsinh Zala | F12: Somnath | G12: Gujarat | H12: Rejected | I12: 108000 | J12: 107010 | K12: =TRIM(Cleaned_CRM_Data!H12) -> Rejected | L12: =IFERROR(VLOOKUP(K12, Status_Mapping!A:B, 2,), "Not Found") -> Rejected | N12: =IF(M12="","",M12-B12) | O12: =IF(OR(I12=108000,I12=130000),"Starter",IF(I12=177000,"Growth","Premium")) -> Starter | P12: =TEXT(B12, "mmmm") -> June | Q12: ="Q"&ROUNDUP(MONTH(B12)/3,0) -> Q2 | R12: =IFERROR(VLOOKUP(TRIM(CLEAN(G12)),Sheet14!$A$2:$B$19,2,FALSE),"Not Mapped") -> West
A13: ="EOS"&TEXT(ROW()-1,"0000") -> EOS0012 | B13: 45817 | C13: FB | D13: =TRIM(CLEAN(SUBSTITUTE(C13,CHAR(160),""))) -> FB | E13: Rohit Yadav | F13: Kota | G13: Rajasthan | H13: Rejected | I13: 130000 | J13: 107011 | K13: =TRIM(Cleaned_CRM_Data!H13) -> Rejected | L13: =IFERROR(VLOOKUP(K13, Status_Mapping!A:B, 2,), "Not Found") -> Rejected | N13: =IF(M13="","",M13-B13) | O13: =IF(OR(I13=108000,I13=130000),"Starter",IF(I13=177000,"Growth","Premium")) -> Starter | P13: =TEXT(B13, "mmmm") -> June | Q13: ="Q"&ROUNDUP(MONTH(B13)/3,0) -> Q2 | R13: =IFERROR(VLOOKUP(TRIM(CLEAN(G13)),Sheet14!$A$2:$B$19,2,FALSE),"Not Mapped") -> West
... A18: ="EOS"&TEXT(ROW()-1,"0000") -> EOS0017 | B18: 45817 | C18: FB | D18: =TRIM(CLEAN(SUBSTITUTE(C18,CHAR(160),""))) -> FB | E18: Kunal Dafda | F18: Rajkot | G18: Gujarat | H18: Rejected | I18: 108000 | J18: 107016 | K18: =TRIM(Cleaned_CRM_Data!H18) -> Rejected | L18: =IFERROR(VLOOKUP(K18, Status_Mapping!A:B, 2,), "Not Found") -> Rejected | N18: =IF(M18="","",M18-B18) | O18: =IF(OR(I18=108000,I18=130000),"Starter",IF(I18=177000,"Growth","Premium")) -> Starter | P18: =TEXT(B18, "mmmm") -> June | Q18: ="Q"&ROUNDUP(MONTH(B18)/3,0) -> Q2 | R18: =IFERROR(VLOOKUP(TRIM(CLEAN(G18)),Sheet14!$A$2:$B$19,2,FALSE),"Not Mapped") -> West
A19: ="EOS"&TEXT(ROW()-1,"0000") -> EOS0018 | B19: 45817 | C19: FB | D19: =TRIM(CLEAN(SUBSTITUTE(C19,CHAR(160),""))) -> FB | E19: Jignesh Parekh | F19: borsad | G19: Gujarat | H19: Deal | I19: 108000 | J19: 107017 | K19: =TRIM(Cleaned_CRM_Data!H19) -> Deal | L19: =IFERROR(VLOOKUP(K19, Status_Mapping!A:B, 2,), "Not Found") -> Converted | M19: 45824 | N19: =IF(M19="","",M19-B19) -> 7 | O19: =IF(OR(I19=108000,I19=130000),"Starter",IF(I19=177000,"Growth","Premium")) -> Starter | P19: =TEXT(B19, "mmmm") -> June | Q19: ="Q"&ROUNDUP(MONTH(B19)/3,0) -> Q2 | R19: =IFERROR(VLOOKUP(TRIM(CLEAN(G19)),Sheet14!$A$2:$B$19,2,FALSE),"Not Mapped") -> West
A20: ="EOS"&TEXT(ROW()-1,"0000") -> EOS0019 | B20: 45817 | C20: FB | D20: =TRIM(CLEAN(SUBSTITUTE(C20,CHAR(160),""))) -> FB | E20: Mushtaq kapadia | F20: Surat | G20: Gujarat | H20: Rejected | I20: 177000 | J20: 107018 | K20: =TRIM(Cleaned_CRM_Data!H20) -> Rejected | L20: =IFERROR(VLOOKUP(K20, Status_Mapping!A:B, 2,), "Not Found") -> Rejected | N20: =IF(M20="","",M20-B20) | O20: =IF(OR(I20=108000,I20=130000),"Starter",IF(I20=177000,"Growth","Premium")) -> Growth | P20: =TEXT(B20, "mmmm") -> June | Q20: ="Q"&ROUNDUP(MONTH(B20)/3,0) -> Q2 | R20: =IFERROR(VLOOKUP(TRIM(CLEAN(G20)),Sheet14!$A$2:$B$19,2,FALSE),"Not Mapped") -> West
A21: ="EOS"&TEXT(ROW()-1,"0000") -> EOS0020 | B21: 45817 | C21: FB | D21: =TRIM(CLEAN(SUBSTITUTE(C21,CHAR(160),""))) -> FB | E21: Ravi Bhetariya | F21: Jamnagar | G21: Gujarat | H21: Rejected | I21: 108000 | J21: 107019 | K21: =TRIM(Cleaned_CRM_Data!H21) -> Rejected | L21: =IFERROR(VLOOKUP(K21, Status_Mapping!A:B, 2,), "Not Found") -> Rejected | N21: =IF(M21="","",M21-B21) | O21: =IF(OR(I21=108000,I21=130000),"Starter",IF(I21=177000,"Growth","Premium")) -> Starter | P21: =TEXT(B21, "mmmm") -> June | Q21: ="Q"&ROUNDUP(MONTH(B21)/3,0) -> Q2 | R21: =IFERROR(VLOOKUP(TRIM(CLEAN(G21)),Sheet14!$A$2:$B$19,2,FALSE),"Not Mapped") -> West
A22: ="EOS"&TEXT(ROW()-1,"0000") -> EOS0021 | B22: 45817 | C22: FB | D22: =TRIM(CLEAN(SUBSTITUTE(C22,CHAR(160),""))) -> FB | E22: Patel Meet | F22: Bavla | G22: Gujarat | H22: Rejected | I22: 108000 | J22: 107020 | K22: deal | L22: =IFERROR(VLOOKUP(K22, Status_Mapping!A:B, 2,), "Not Found") -> Converted | N22: =IF(M22="","",M22-B22) | O22: =IF(OR(I22=108000,I22=130000),"Starter",IF(I22=177000,"Growth","Premium")) -> Starter | P22: =TEXT(B22, "mmmm") -> June | Q22: ="Q"&ROUNDUP(MONTH(B22)/3,0) -> Q2 | R22: =IFERROR(VLOOKUP(TRIM(CLEAN(G22)),Sheet14!$A$2:$B$19,2,FALSE),"Not Mapped") -> West
A23: ="EOS"&TEXT(ROW()-1,"0000") -> EOS0022 | B23: 45817 | C23: FB | D23: =TRIM(CLEAN(SUBSTITUTE(C23,CHAR(160),""))) -> FB | E23: Jagrut Jadeja | F23: Bantwa | G23: Gujarat | H23: Rejected | I23: 108000 | J23: 107021 | K23: =TRIM(Cleaned_CRM_Data!H23) -> Rejected | L23: =IFERROR(VLOOKUP(K23, Status_Mapping!A:B, 2,), "Not Found") -> Rejected | N23: =IF(M23="","",M23-B23) | O23: =IF(OR(I23=108000,I23=130000),"Starter",IF(I23=177000,"Growth","Premium")) -> Starter | P23: =TEXT(B23, "mmmm") -> June | Q23: ="Q"&ROUNDUP(MONTH(B23)/3,0) -> Q2 | R23: =IFERROR(VLOOKUP(TRIM(CLEAN(G23)),Sheet14!$A$2:$B$19,2,FALSE),"Not Mapped") -> West
A24: ="EOS"&TEXT(ROW()-1,"0000") -> EOS0023 | B24: 45817 | C24: FB | D24: =TRIM(CLEAN(SUBSTITUTE(C24,CHAR(160),""))) -> FB | E24: Gulamabbas Meghani | F24: Bhavnagar | G24: Gujarat | H24: Rejected | I24: 130000 | J24: 107022 | K24: =TRIM(Cleaned_CRM_Data!H24) -> Rejected | L24: =IFERROR(VLOOKUP(K24, Status_Mapping!A:B, 2,), "Not Found") -> Rejected | N24: =IF(M24="","",M24-B24) | O24: =IF(OR(I24=108000,I24=130000),"Starter",IF(I24=177000,"Growth","Premium")) -> Starter | P24: =TEXT(B24, "mmmm") -> June | Q24: ="Q"&ROUNDUP(MONTH(B24)/3,0) -> Q2 | R24: =IFERROR(VLOOKUP(TRIM(CLEAN(G24)),Sheet14!$A$2:$B$19,2,FALSE),"Not Mapped") -> West
A25: ="EOS"&TEXT(ROW()-1,"0000") -> EOS0024 | B25: 45817 | C25: FB | D25: =TRIM(CLEAN(SUBSTITUTE(C25,CHAR(160),""))) -> FB | E25: 𝕯ɪʟɪᴘ Ⱥᴄʜᴀʀʏᴀ | F25: Tharad | G25: Gujarat | H25: Rejected | I25: 108000 | J25: 107023 | K25: =TRIM(Cleaned_CRM_Data!H25) -> Rejected | L25: =IFERROR(VLOOKUP(K25, Status_Mapping!A:B, 2,), "Not Found") -> Rejected | N25: =IF(M25="","",M25-B25) | O25: =IF(OR(I25=108000,I25=130000),"Starter",IF(I25=177000,"Growth","Premium")) -> Starter | P25: =TEXT(B25, "mmmm") -> June | Q25: ="Q"&ROUNDUP(MONTH(B25)/3,0) -> Q2 | R25: =IFERROR(VLOOKUP(TRIM(CLEAN(G25)),Sheet14!$A$2:$B$19,2,FALSE),"Not Mapped") -> West
A26: ="EOS"&TEXT(ROW()-1,"0000") -> EOS0025 | B26: 45817 | C26: FB | D26: =TRIM(CLEAN(SUBSTITUTE(C26,CHAR(160),""))) -> FB | E26: mayur_ahir_3543 | F26: Rajkot | G26: Gujarat | H26: Rejected | I26: 108000 | J26: 107024 | K26: =TRIM(Cleaned_CRM_Data!H26) -> Rejected | L26: =IFERROR(VLOOKUP(K26, Status_Mapping!A:B, 2,), "Not Found") -> Rejected | N26: =IF(M26="","",M26-B26) | O26: =IF(OR(I26=108000,I26=130000),"Starter",IF(I26=177000,"Growth","Premium")) -> Starter | P26: =TEXT(B26, "mmmm") -> June | Q26: ="Q"&ROUNDUP(MONTH(B26)/3,0) -> Q2 | R26: =IFERROR(VLOOKUP(TRIM(CLEAN(G26)),Sheet14!$A$2:$B$19,2,FALSE),"Not Mapped") -> West
A27: ="EOS"&TEXT(ROW()-1,"0000") -> EOS0026 | B27: 45817 | C27: FB | D27: =TRIM(CLEAN(SUBSTITUTE(C27,CHAR(160),""))) -> FB | E27: Patel Jay | F27: Khambhat | G27: Gujarat | H27: Rejected | I27: 108000 | J27: 107025 | K27: =TRIM(Cleaned_CRM_Data!H27) -> Rejected | L27: =IFERROR(VLOOKUP(K27, Status_Mapping!A:B, 2,), "Not Found") -> Rejected | N27: =IF(M27="","",M27-B27) | O27: =IF(OR(I27=108000,I27=130000),"Starter",IF(I27=177000,"Growth","Premium")) -> Starter | P27: =TEXT(B27, "mmmm") -> June | Q27: ="Q"&ROUNDUP(MONTH(B27)/3,0) -> Q2 | R27: =IFERROR(VLOOKUP(TRIM(CLEAN(G27)),Sheet14!$A$2:$B$19,2,FALSE),"Not Mapped") -> West
A28: ="EOS"&TEXT(ROW()-1,"0000") -> EOS0027 | B28: 45817 | C28: FB | D28: =TRIM(CLEAN(SUBSTITUTE(C28,CHAR(160),""))) -> FB | E28: Keval Makwana | F28: Rajkot | G28: Gujarat | H28: Rejected | I28: 108000 | J28: 107026 | K28: =TRIM(Cleaned_CRM_Data!H28) -> Rejected | L28: =IFERROR(VLOOKUP(K28, Status_Mapping!A:B, 2,), "Not Found") -> Rejected | N28: =IF(M28="","",M28-B28) | O28: =IF(OR(I28=108000,I28=130000),"Starter",IF(I28=177000,"Growth","Premium")) -> Starter | P28: =TEXT(B28, "mmmm") -> June | Q28: ="Q"&ROUNDUP(MONTH(B28)/3,0) -> Q2 | R28: =IFERROR(VLOOKUP(TRIM(CLEAN(G28)),Sheet14!$A$2:$B$19,2,FALSE),"Not Mapped") -> West
A29: ="EOS"&TEXT(ROW()-1,"0000") -> EOS0028 | B29: 45817 | C29: FB | D29: =TRIM(CLEAN(SUBSTITUTE(C29,CHAR(160),""))) -> FB | E29: Mehul | F29: Mota chiloda | G29: Gujarat | H29: Rejected | I29: 130000 | J29: 107027 | K29: =TRIM(Cleaned_CRM_Data!H29) -> Rejected | L29: =IFERROR(VLOOKUP(K29, Status_Mapping!A:B, 2,), "Not Found") -> Rejected | N29: =IF(M29="","",M29-B29) | O29: =IF(OR(I29=108000,I29=130000),"Starter",IF(I29=177000,"Growth","Premium")) -> Starter | P29: =TEXT(B29, "mmmm") -> June | Q29: ="Q"&ROUNDUP(MONTH(B29)/3,0) -> Q2 | R29: =IFERROR(VLOOKUP(TRIM(CLEAN(G29)),Sheet14!$A$2:$B$19,2,FALSE),"Not Mapped") -> West
A30: ="EOS"&TEXT(ROW()-1,"0000") -> EOS0029 | B30: 45817 | C30: FB | D30: =TRIM(CLEAN(SUBSTITUTE(C30,CHAR(160),""))) -> FB | E30: Shànú Pàrmàr | F30: Mehsana | G30: Gujarat | H30: Rejected | I30: 130000 | J30: 107028 | K30: =TRIM(Cleaned_CRM_Data!H30) -> Rejected | L30: =IFERROR(VLOOKUP(K30, Status_Mapping!A:B, 2,), "Not Found") -> Rejected | N30: =IF(M30="","",M30-B30) | O30: =IF(OR(I30=108000,I30=130000),"Starter",IF(I30=177000,"Growth","Premium")) -> Starter | P30: =TEXT(B30, "mmmm") -> June | Q30: ="Q"&ROUNDUP(MONTH(B30)/3,0) -> Q2 | R30: =IFERROR(VLOOKUP(TRIM(CLEAN(G30)),Sheet14!$A$2:$B$19,2,FALSE),"Not Mapped") -> West
A31: ="EOS"&TEXT(ROW()-1,"0000") -> EOS0030 | B31: 45817 | C31: FB | D31: =TRIM(CLEAN(SUBSTITUTE(C31,CHAR(160),""))) -> FB | E31: ak_dhapa_2287 | F31: Jamnagar | G31: Gujarat | H31: Rejected | I31: 108000 | J31: 107029 | K31: =TRIM(Cleaned_CRM_Data!H31) -> Rejected | L31: =IFERROR(VLOOKUP(K31, Status_Mapping!A:B, 2,), "Not Found") -> Rejected | N31: =IF(M31="","",M31-B31) | O31: =IF(OR(I31=108000,I31=130000),"Starter",IF(I31=177000,"Growth","Premium")) -> Starter | P31: =TEXT(B31, "mmmm") -> June | Q31: ="Q"&ROUNDUP(MONTH(B31)/3,0) -> Q2 | R31: =IFERROR(VLOOKUP(TRIM(CLEAN(G31)),Sheet14!$A$2:$B$19,2,FALSE),"Not Mapped") -> West
A32: ="EOS"&TEXT(ROW()-1,"0000") -> EOS0031 | B32: 45817 | C32: FB | D32: =TRIM(CLEAN(SUBSTITUTE(C32,CHAR(160),""))) -> FB | E32: Rakesh Yogi | F32: Patan | G32: Gujarat | H32: Rejected | I32: 108000 | J32: 107030 | K32: =TRIM(Cleaned_CRM_Data!H32) -> Rejected | L32: =IFERROR(VLOOKUP(K32, Status_Mapping!A:B, 2,), "Not Found") -> Rejected | N32: =IF(M32="","",M32-B32) | O32: =IF(OR(I32=108000,I32=130000),"Starter",IF(I32=177000,"Growth","Premium")) -> Starter | P32: =TEXT(B32, "mmmm") -> June | Q32: ="Q"&ROUNDUP(MONTH(B32)/3,0) -> Q2 | R32: =IFERROR(VLOOKUP(TRIM(CLEAN(G32)),Sheet14!$A$2:$B$19,2,FALSE),"Not Mapped") -> West
A33: ="EOS"&TEXT(ROW()-1,"0000") -> EOS0032 | B33: 45817 | C33: FB | D33: =TRIM(CLEAN(SUBSTITUTE(C33,CHAR(160),""))) -> FB | E33: Vijay Patel | F33: Nadiad | G33: Gujarat | H33: Rejected | I33: 108000 | J33: 107031 | K33: =TRIM(Cleaned_CRM_Data!H33) -> Rejected | L33: =IFERROR(VLOOKUP(K33, Status_Mapping!A:B, 2,), "Not Found") -> Rejected | N33: =IF(M33="","",M33-B33) | O33: =IF(OR(I33=108000,I33=130000),"Starter",IF(I33=177000,"Growth","Premium")) -> Starter | P33: =TEXT(B33, "mmmm") -> June | Q33: ="Q"&ROUNDUP(MONTH(B33)/3,0) -> Q2 | R33: =IFERROR(VLOOKUP(TRIM(CLEAN(G33)),Sheet14!$A$2:$B$19,2,FALSE),"Not Mapped") -> West
A34: ="EOS"&TEXT(ROW()-1,"0000") -> EOS0033 | B34: 45817 | C34: FB | D34: =TRIM(CLEAN(SUBSTITUTE(C34,CHAR(160),""))) -> FB | E34: $oyeb | F34: Halol | G34: Gujarat | H34: Rejected | I34: 177000 | J34: 107032 | K34: =TRIM(Cleaned_CRM_Data!H34) -> Rejected | L34: =IFERROR(VLOOKUP(K34, Status_Mapping!A:B, 2,), "Not Found") -> Rejected | N34: =IF(M34="","",M34-B34) | O34: =IF(OR(I34=108000,I34=130000),"Starter",IF(I34=177000,"Growth","Premium")) -> Growth | P34: =TEXT(B34, "mmmm") -> June | Q34: ="Q"&ROUNDUP(MONTH(B34)/3,0) -> Q2 | R34: =IFERROR(VLOOKUP(TRIM(CLEAN(G34)),Sheet14!$A$2:$B$19,2,FALSE),"Not Mapped") -> West
... A46: ="EOS"&TEXT(ROW()-1,"0000") -> EOS0045 | B46: 45819 | C46: FB | D46: =TRIM(CLEAN(SUBSTITUTE(C46,CHAR(160),""))) -> FB | E46: Hitesh Parmar | F46: Ahmedabad | G46: Gujarat | H46: Rejected | I46: 130000 | J46: 107044 | K46: =TRIM(Cleaned_CRM_Data!H46) -> Rejected | L46: =IFERROR(VLOOKUP(K46, Status_Mapping!A:B, 2,), "Not Found") -> Rejected | N46: =IF(M46="","",M46-B46) | O46: =IF(OR(I46=108000,I46=130000),"Starter",IF(I46=177000,"Growth","Premium")) -> Starter | P46: =TEXT(B46, "mmmm") -> June | Q46: ="Q"&ROUNDUP(MONTH(B46)/3,0) -> Q2 | R46: =IFERROR(VLOOKUP(TRIM(CLEAN(G46)),Sheet14!$A$2:$B$19,2,FALSE),"Not Mapped") -> West
A47: ="EOS"&TEXT(ROW()-1,"0000") -> EOS0046 | B47: 45819 | C47: FB | D47: =TRIM(CLEAN(SUBSTITUTE(C47,CHAR(160),""))) -> FB | E47: 0 | F47: Kheralu | G47: Gujarat | H47: Rejected | I47: 108000 | J47: 107045 | K47: =TRIM(Cleaned_CRM_Data!H47) -> Rejected | L47: =IFERROR(VLOOKUP(K47, Status_Mapping!A:B, 2,), "Not Found") -> Rejected | N47: =IF(M47="","",M47-B47) | O47: =IF(OR(I47=108000,I47=130000),"Starter",IF(I47=177000,"Growth","Premium")) -> Starter | P47: =TEXT(B47, "mmmm") -> June | Q47: ="Q"&ROUNDUP(MONTH(B47)/3,0) -> Q2 | R47: =IFERROR(VLOOKUP(TRIM(CLEAN(G47)),Sheet14!$A$2:$B$19,2,FALSE),"Not Mapped") -> West
A48: ="EOS"&TEXT(ROW()-1,"0000") -> EOS0047 | B48: 45819 | C48: FB | D48: =TRIM(CLEAN(SUBSTITUTE(C48,CHAR(160),""))) -> FB | E48: karmrajsinh vadher | F48: Jamnagar | G48: Gujarat | H48: Rejected | I48: 108000 | J48: 107046 | K48: =TRIM(Cleaned_CRM_Data!H48) -> Rejected | L48: =IFERROR(VLOOKUP(K48, Status_Mapping!A:B, 2,), "Not Found") -> Rejected | N48: =IF(M48="","",M48-B48) | O48: =IF(OR(I48=108000,I48=130000),"Starter",IF(I48=177000,"Growth","Premium")) -> Starter | P48: =TEXT(B48, "mmmm") -> June | Q48: ="Q"&ROUNDUP(MONTH(B48)/3,0) -> Q2 | R48: =IFERROR(VLOOKUP(TRIM(CLEAN(G48)),Sheet14!$A$2:$B$19,2,FALSE),"Not Mapped") -> West
A49: ="EOS"&TEXT(ROW()-1,"0000") -> EOS0048 | B49: 45819 | C49: FB | D49: =TRIM(CLEAN(SUBSTITUTE(C49,CHAR(160),""))) -> FB | E49: Vivek Diyora | F49: Surat | G49: Gujarat | H49: Rejected | I49: 130000 | J49: 107047 | K49: =TRIM(Cleaned_CRM_Data!H49) -> Rejected | L49: =IFERROR(VLOOKUP(K49, Status_Mapping!A:B, 2,), "Not Found") -> Rejected | N49: =IF(M49="","",M49-B49) | O49: =IF(OR(I49=108000,I49=130000),"Starter",IF(I49=177000,"Growth","Premium")) -> Starter | P49: =TEXT(B49, "mmmm") -> June | Q49: ="Q"&ROUNDUP(MONTH(B49)/3,0) -> Q2 | R49: =IFERROR(VLOOKUP(TRIM(CLEAN(G49)),Sheet14!$A$2:$B$19,2,FALSE),"Not Mapped") -> West
A50: ="EOS"&TEXT(ROW()-1,"0000") -> EOS0049 | B50: 45819 | C50: FB | D50: =TRIM(CLEAN(SUBSTITUTE(C50,CHAR(160),""))) -> FB | E50: Rajendrasinh Parmar | F50: Gandhinagar | G50: Gujarat | H50: Rejected | I50: 108000 | J50: 107048 | K50: =TRIM(Cleaned_CRM_Data!H50) -> Rejected | L50: =IFERROR(VLOOKUP(K50, Status_Mapping!A:B, 2,), "Not Found") -> Rejected | N50: =IF(M50="","",M50-B50) | O50: =IF(OR(I50=108000,I50=130000),"Starter",IF(I50=177000,"Growth","Premium")) -> Starter | P50: =TEXT(B50, "mmmm") -> June | Q50: ="Q"&ROUNDUP(MONTH(B50)/3,0) -> Q2 | R50: =IFERROR(VLOOKUP(TRIM(CLEAN(G50)),Sheet14!$A$2:$B$19,2,FALSE),"Not Mapped") -> West
A51: ="EOS"&TEXT(ROW()-1,"0000") -> EOS0050 | B51: 45819 | C51: FB | D51: =TRIM(CLEAN(SUBSTITUTE(C51,CHAR(160),""))) -> FB | E51: Gunjan // gp... | F51: Patan | G51: Gujarat | H51: Rejected | I51: 308000 | J51: 107049 | K51: =TRIM(Cleaned_CRM_Data!H51) -> Rejected | L51: =IFERROR(VLOOKUP(K51, Status_Mapping!A:B, 2,), "Not Found") -> Rejected | N51: =IF(M51="","",M51-B51) | O51: =IF(OR(I51=108000,I51=130000),"Starter",IF(I51=177000,"Growth","Premium")) -> Premium | P51: =TEXT(B51, "mmmm") -> June | Q51: ="Q"&ROUNDUP(MONTH(B51)/3,0) -> Q2 | R51: =IFERROR(VLOOKUP(TRIM(CLEAN(G51)),Sheet14!$A$2:$B$19,2,FALSE),"Not Mapped") -> West
A52: ="EOS"&TEXT(ROW()-1,"0000") -> EOS0051 | B52: 45819 | C52: FB | D52: =TRIM(CLEAN(SUBSTITUTE(C52,CHAR(160),""))) -> FB | E52: 𝐏 𝐀 𝐑 𝐓 𝐇 | F52: Surendranagar | G52: Gujarat | H52: Rejected | I52: 130000 | J52: 107050 | K52: =TRIM(Cleaned_CRM_Data!H52) -> Rejected | L52: =IFERROR(VLOOKUP(K52, Status_Mapping!A:B, 2,), "Not Found") -> Rejected | N52: =IF(M52="","",M52-B52) | O52: =IF(OR(I52=108000,I52=130000),"Starter",IF(I52=177000,"Growth","Premium")) -> Starter | P52: =TEXT(B52, "mmmm") -> June | Q52: ="Q"&ROUNDUP(MONTH(B52)/3,0) -> Q2 | R52: =IFERROR(VLOOKUP(TRIM(CLEAN(G52)),Sheet14!$A$2:$B$19,2,FALSE),"Not Mapped") -> West
A53: ="EOS"&TEXT(ROW()-1,"0000") -> EOS0052 | B53: 45819 | C53: FB | D53: =TRIM(CLEAN(SUBSTITUTE(C53,CHAR(160),""))) -> FB | E53: D.m. Ahir | F53: Khambhalia | G53: Gujarat | H53: Rejected | I53: 177000 | J53: 107051 | K53: =TRIM(Cleaned_CRM_Data!H53) -> Rejected | L53: =IFERROR(VLOOKUP(K53, Status_Mapping!A:B, 2,), "Not Found") -> Rejected | N53: =IF(M53="","",M53-B53) | O53: =IF(OR(I53=108000,I53=130000),"Starter",IF(I53=177000,"Growth","Premium")) -> Growth | P53: =TEXT(B53, "mmmm") -> June | Q53: ="Q"&ROUNDUP(MONTH(B53)/3,0) -> Q2 | R53: =IFERROR(VLOOKUP(TRIM(CLEAN(G53)),Sheet14!$A$2:$B$19,2,FALSE),"Not Mapped") -> West
A54: ="EOS"&TEXT(ROW()-1,"0000") -> EOS0053 | B54: 45819 | C54: FB | D54: =TRIM(CLEAN(SUBSTITUTE(C54,CHAR(160),""))) -> FB | E54: Sandip Solanki | F54: Borsad | G54: Gujarat | H54: Rejected | I54: 108000 | J54: 107052 | K54: =TRIM(Cleaned_CRM_Data!H54) -> Rejected | L54: =IFERROR(VLOOKUP(K54, Status_Mapping!A:B, 2,), "Not Found") -> Rejected | N54: =IF(M54="","",M54-B54) | O54: =IF(OR(I54=108000,I54=130000),"Starter",IF(I54=177000,"Growth","Premium")) -> Starter | P54: =TEXT(B54, "mmmm") -> June | Q54: ="Q"&ROUNDUP(MONTH(B54)/3,0) -> Q2 | R54: =IFERROR(VLOOKUP(TRIM(CLEAN(G54)),Sheet14!$A$2:$B$19,2,FALSE),"Not Mapped") -> West
A55: ="EOS"&TEXT(ROW()-1,"0000") -> EOS0054 | B55: 45819 | C55: FB | D55: =TRIM(CLEAN(SUBSTITUTE(C55,CHAR(160),""))) -> FB | E55: Ammar Vahora | F55: Anand | G55: Gujarat | H55: Rejected | I55: 108000 | J55: 107053 | K55: =TRIM(Cleaned_CRM_Data!H55) -> Rejected | L55: =IFERROR(VLOOKUP(K55, Status_Mapping!A:B, 2,), "Not Found") -> Rejected | N55: =IF(M55="","",M55-B55) | O55: =IF(OR(I55=108000,I55=130000),"Starter",IF(I55=177000,"Growth","Premium")) -> Starter | P55: =TEXT(B55, "mmmm") -> June | Q55: ="Q"&ROUNDUP(MONTH(B55)/3,0) -> Q2 | R55: =IFERROR(VLOOKUP(TRIM(CLEAN(G55)),Sheet14!$A$2:$B$19,2,FALSE),"Not Mapped") -> West
A56: ="EOS"&TEXT(ROW()-1,"0000") -> EOS0055 | B56: 45819 | C56: FB | D56: =TRIM(CLEAN(SUBSTITUTE(C56,CHAR(160),""))) -> FB | E56: Kartik Patel | F56: Patan | G56: Gujarat | H56: Rejected | I56: 130000 | J56: 107054 | K56: =TRIM(Cleaned_CRM_Data!H56) -> Rejected | L56: =IFERROR(VLOOKUP(K56, Status_Mapping!A:B, 2,), "Not Found") -> Rejected | N56: =IF(M56="","",M56-B56) | O56: =IF(OR(I56=108000,I56=130000),"Starter",IF(I56=177000,"Growth","Premium")) -> Starter | P56: =TEXT(B56, "mmmm") -> June | Q56: ="Q"&ROUNDUP(MONTH(B56)/3,0) -> Q2 | R56: =IFERROR(VLOOKUP(TRIM(CLEAN(G56)),Sheet14!$A$2:$B$19,2,FALSE),"Not Mapped") -> West
A57: ="EOS"&TEXT(ROW()-1,"0000") -> EOS0056 | B57: 45819 | C57: FB | D57: =TRIM(CLEAN(SUBSTITUTE(C57,CHAR(160),""))) -> FB | E57: 🆂🅳🅷 🅽🅸🆁🆄🅳🅷🆂🅸🅽🅷 🅳 | F57: Mundra | G57: Gujarat | H57: Rejected | I57: 177000 | J57: 107055 | K57: =TRIM(Cleaned_CRM_Data!H57) -> Rejected | L57: =IFERROR(VLOOKUP(K57, Status_Mapping!A:B, 2,), "Not Found") -> Rejected | N57: =IF(M57="","",M57-B57) | O57: =IF(OR(I57=108000,I57=130000),"Starter",IF(I57=177000,"Growth","Premium")) -> Growth | P57: =TEXT(B57, "mmmm") -> June | Q57: ="Q"&ROUNDUP(MONTH(B57)/3,0) -> Q2 | R57: =IFERROR(VLOOKUP(TRIM(CLEAN(G57)),Sheet14!$A$2:$B$19,2,FALSE),"Not Mapped") -> West
A58: ="EOS"&TEXT(ROW()-1,"0000") -> EOS0057 | B58: 45819 | C58: FB | D58: =TRIM(CLEAN(SUBSTITUTE(C58,CHAR(160),""))) -> FB | E58: 0 | F58: Talala | G58: Gujarat | H58: Rejected | I58: 108000 | J58: 107056 | K58: =TRIM(Cleaned_CRM_Data!H58) -> Rejected | L58: =IFERROR(VLOOKUP(K58, Status_Mapping!A:B, 2,), "Not Found") -> Rejected | N58: =IF(M58="","",M58-B58) | O58: =IF(OR(I58=108000,I58=130000),"Starter",IF(I58=177000,"Growth","Premium")) -> Starter | P58: =TEXT(B58, "mmmm") -> June | Q58: ="Q"&ROUNDUP(MONTH(B58)/3,0) -> Q2 | R58: =IFERROR(VLOOKUP(TRIM(CLEAN(G58)),Sheet14!$A$2:$B$19,2,FALSE),"Not Mapped") -> West
A59: ="EOS"&TEXT(ROW()-1,"0000") -> EOS0058 | B59: 45819 | C59: FB | D59: =TRIM(CLEAN(SUBSTITUTE(C59,CHAR(160),""))) -> FB | E59: Asfak Parasara | F59: Wankaner | G59: Gujarat | H59: Rejected | I59: 130000 | J59: 107057 | K59: =TRIM(Cleaned_CRM_Data!H59) -> Rejected | L59: =IFERROR(VLOOKUP(K59, Status_Mapping!A:B, 2,), "Not Found") -> Rejected | N59: =IF(M59="","",M59-B59) | O59: =IF(OR(I59=108000,I59=130000),"Starter",IF(I59=177000,"Growth","Premium")) -> Starter | P59: =TEXT(B59, "mmmm") -> June | Q59: ="Q"&ROUNDUP(MONTH(B59)/3,0) -> Q2 | R59: =IFERROR(VLOOKUP(TRIM(CLEAN(G59)),Sheet14!$A$2:$B$19,2,FALSE),"Not Mapped") -> West
A60: ="EOS"&TEXT(ROW()-1,"0000") -> EOS0059 | B60: 45819 | C60: FB | D60: =TRIM(CLEAN(SUBSTITUTE(C60,CHAR(160),""))) -> FB | E60: Vaibhav Pandey | F60: Karwi | G60: Uttar Pradesh | H60: Deal | I60: 130000 | J60: 107058 | K60: =TRIM(Cleaned_CRM_Data!H60) -> Deal | L60: =IFERROR(VLOOKUP(K60, Status_Mapping!A:B, 2,), "Not Found") -> Converted | N60: =IF(M60="","",M60-B60) | O60: =IF(OR(I60=108000,I60=130000),"Starter",IF(I60=177000,"Growth","Premium")) -> Starter | P60: =TEXT(B60, "mmmm") -> June | Q60: ="Q"&ROUNDUP(MONTH(B60)/3,0) -> Q2 | R60: =IFERROR(VLOOKUP(TRIM(CLEAN(G60)),Sheet14!$A$2:$B$19,2,FALSE),"Not Mapped") -> North
A61: ="EOS"&TEXT(ROW()-1,"0000") -> EOS0060 | B61: 45819 | C61: FB | D61: =TRIM(CLEAN(SUBSTITUTE(C61,CHAR(160),""))) -> FB | E61: AVDEEP | F61: Rajkot | G61: Gujarat | H61: Rejected | I61: 177000 | J61: 107059 | K61: =TRIM(Cleaned_CRM_Data!H61) -> Rejected | L61: =IFERROR(VLOOKUP(K61, Status_Mapping!A:B, 2,), "Not Found") -> Rejected | N61: =IF(M61="","",M61-B61) | O61: =IF(OR(I61=108000,I61=130000),"Starter",IF(I61=177000,"Growth","Premium")) -> Growth | P61: =TEXT(B61, "mmmm") -> June | Q61: ="Q"&ROUNDUP(MONTH(B61)/3,0) -> Q2 | R61: =IFERROR(VLOOKUP(TRIM(CLEAN(G61)),Sheet14!$A$2:$B$19,2,FALSE),"Not Mapped") -> West
A62: ="EOS"&TEXT(ROW()-1,"0000") -> EOS0061 | B62: 45819 | C62: FB | D62: =TRIM(CLEAN(SUBSTITUTE(C62,CHAR(160),""))) -> FB | E62: Saumil Mistry | F62: Ahmedabad | G62: Gujarat | H62: Rejected | I62: 108000 | J62: 107060 | K62: =TRIM(Cleaned_CRM_Data!H62) -> Rejected | L62: =IFERROR(VLOOKUP(K62, Status_Mapping!A:B, 2,), "Not Found") -> Rejected | N62: =IF(M62="","",M62-B62) | O62: =IF(OR(I62=108000,I62=130000),"Starter",IF(I62=177000,"Growth","Premium")) -> Starter | P62: =TEXT(B62, "mmmm") -> June | Q62: ="Q"&ROUNDUP(MONTH(B62)/3,0) -> Q2 | R62: =IFERROR(VLOOKUP(TRIM(CLEAN(G62)),Sheet14!$A$2:$B$19,2,FALSE),"Not Mapped") -> West
A63: ="EOS"&TEXT(ROW()-1,"0000") -> EOS0062 | B63: 45819 | C63: FB | D63: =TRIM(CLEAN(SUBSTITUTE(C63,CHAR(160),""))) -> FB | E63: M. P. Joshi Bhudev | F63: Tharad | G63: Gujarat | H63: Rejected | I63: 108000 | J63: 107061 | K63: =TRIM(Cleaned_CRM_Data!H63) -> Rejected | L63: =IFERROR(VLOOKUP(K63, Status_Mapping!A:B, 2,), "Not Found") -> Rejected | N63: =IF(M63="","",M63-B63) | O63: =IF(OR(I63=108000,I63=130000),"Starter",IF(I63=177000,"Growth","Premium")) -> Starter | P63: =TEXT(B63, "mmmm") -> June | Q63: ="Q"&ROUNDUP(MONTH(B63)/3,0) -> Q2 | R63: =IFERROR(VLOOKUP(TRIM(CLEAN(G63)),Sheet14!$A$2:$B$19,2,FALSE),"Not Mapped") -> West
A64: ="EOS"&TEXT(ROW()-1,"0000") -> EOS0063 | B64: 45819 | C64: FB | D64: =TRIM(CLEAN(SUBSTITUTE(C64,CHAR(160),""))) -> FB | E64: રણા વિશ્વજીતસિંહ સુરપાલસિંહ | F64: Motisarsan | G64: Gujarat | H64: Rejected | I64: 130000 | J64: 107062 | K64: =TRIM(Cleaned_CRM_Data!H64) -> Rejected | L64: =IFERROR(VLOOKUP(K64, Status_Mapping!A:B, 2,), "Not Found") -> Rejected | N64: =IF(M64="","",M64-B64) | O64: =IF(OR(I64=108000,I64=130000),"Starter",IF(I64=177000,"Growth","Premium")) -> Starter | P64: =TEXT(B64, "mmmm") -> June | Q64: ="Q"&ROUNDUP(MONTH(B64)/3,0) -> Q2 | R64: =IFERROR(VLOOKUP(TRIM(CLEAN(G64)),Sheet14!$A$2:$B$19,2,FALSE),"Not Mapped") -> West
A65: ="EOS"&TEXT(ROW()-1,"0000") -> EOS0064 | B65: 45819 | C65: FB | D65: =TRIM(CLEAN(SUBSTITUTE(C65,CHAR(160),""))) -> FB | E65: PATHAN | F65: Ahmedabad | G65: Gujarat | H65: Rejected | I65: 108000 | J65: 107063 | K65: =TRIM(Cleaned_CRM_Data!H65) -> Rejected | L65: =IFERROR(VLOOKUP(K65, Status_Mapping!A:B, 2,), "Not Found") -> Rejected | N65: =IF(M65="","",M65-B65) | O65: =IF(OR(I65=108000,I65=130000),"Starter",IF(I65=177000,"Growth","Premium")) -> Starter | P65: =TEXT(B65, "mmmm") -> June | Q65: ="Q"&ROUNDUP(MONTH(B65)/3,0) -> Q2 | R65: =IFERROR(VLOOKUP(TRIM(CLEAN(G65)),Sheet14!$A$2:$B$19,2,FALSE),"Not Mapped") -> West
A66: ="EOS"&TEXT(ROW()-1,"0000") -> EOS0065 | B66: 45819 | C66: FB | D66: =TRIM(CLEAN(SUBSTITUTE(C66,CHAR(160),""))) -> FB | E66: Narendrasinh Parmar | F66: Banaskantha | G66: Gujarat | H66: Rejected | I66: 130000 | J66: 107064 | K66: =TRIM(Cleaned_CRM_Data!H66) -> Rejected | L66: =IFERROR(VLOOKUP(K66, Status_Mapping!A:B, 2,), "Not Found") -> Rejected | N66: =IF(M66="","",M66-B66) | O66: =IF(OR(I66=108000,I66=130000),"Starter",IF(I66=177000,"Growth","Premium")) -> Starter | P66: =TEXT(B66, "mmmm") -> June | Q66: ="Q"&ROUNDUP(MONTH(B66)/3,0) -> Q2 | R66: =IFERROR(VLOOKUP(TRIM(CLEAN(G66)),Sheet14!$A$2:$B$19,2,FALSE),"Not Mapped") -> West
A67: ="EOS"&TEXT(ROW()-1,"0000") -> EOS0066 | B67: 45819 | C67: FB | D67: =TRIM(CLEAN(SUBSTITUTE(C67,CHAR(160),""))) -> FB | E67: Dev Gandhi | F67: Ahmedabad | G67: Gujarat | H67: Rejected | I67: 108000 | J67: 107065 | K67: =TRIM(Cleaned_CRM_Data!H67) -> Rejected | L67: =IFERROR(VLOOKUP(K67, Status_Mapping!A:B, 2,), "Not Found") -> Rejected | N67: =IF(M67="","",M67-B67) | O67: =IF(OR(I67=108000,I67=130000),"Starter",IF(I67=177000,"Growth","Premium")) -> Starter | P67: =TEXT(B67, "mmmm") -> June | Q67: ="Q"&ROUNDUP(MONTH(B67)/3,0) -> Q2 | R67: =IFERROR(VLOOKUP(TRIM(CLEAN(G67)),Sheet14!$A$2:$B$19,2,FALSE),"Not Mapped") -> West
A68: ="EOS"&TEXT(ROW()-1,"0000") -> EOS0067 | B68: 45819 | C68: FB | D68: =TRIM(CLEAN(SUBSTITUTE(C68,CHAR(160),""))) -> FB | E68: Safdar Shaikh | F68: MANGROL | G68: Gujarat | H68: Rejected | I68: 130000 | J68: 107066 | K68: =TRIM(Cleaned_CRM_Data!H68) -> Rejected | L68: =IFERROR(VLOOKUP(K68, Status_Mapping!A:B, 2,), "Not Found") -> Rejected | N68: =IF(M68="","",M68-B68) | O68: =IF(OR(I68=108000,I68=130000),"Starter",IF(I68=177000,"Growth","Premium")) -> Starter | P68: =TEXT(B68, "mmmm") -> June | Q68: ="Q"&ROUNDUP(MONTH(B68)/3,0) -> Q2 | R68: =IFERROR(VLOOKUP(TRIM(CLEAN(G68)),Sheet14!$A$2:$B$19,2,FALSE),"Not Mapped") -> West
A69: ="EOS"&TEXT(ROW()-1,"0000") -> EOS0068 | B69: 45819 | C69: FB | D69: =TRIM(CLEAN(SUBSTITUTE(C69,CHAR(160),""))) -> FB | E69: himanshu Amin | F69: Ahmedabad | G69: Gujarat | H69: Rejected | I69: 130000 | J69: 107067 | K69: =TRIM(Cleaned_CRM_Data!H69) -> Rejected | L69: =IFERROR(VLOOKUP(K69, Status_Mapping!A:B, 2,), "Not Found") -> Rejected | N69: =IF(M69="","",M69-B69) | O69: =IF(OR(I69=108000,I69=130000),"Starter",IF(I69=177000,"Growth","Premium")) -> Starter | P69: =TEXT(B69, "mmmm") -> June | Q69: ="Q"&ROUNDUP(MONTH(B69)/3,0) -> Q2 | R69: =IFERROR(VLOOKUP(TRIM(CLEAN(G69)),Sheet14!$A$2:$B$19,2,FALSE),"Not Mapped") -> West
A70: ="EOS"&TEXT(ROW()-1,"0000") -> EOS0069 | B70: 16/06/2025 | C70: FB | D70: =TRIM(CLEAN(SUBSTITUTE(C70,CHAR(160),""))) -> FB | E70: Kaushik Ahir | F70: Daman | G70: Gujarat | H70: Rejected | I70: 108000 | J70: 107068 | K70: =TRIM(Cleaned_CRM_Data!H70) -> Rejected | L70: =IFERROR(VLOOKUP(K70, Status_Mapping!A:B, 2,), "Not Found") -> Rejected | N70: =IF(M70="","",M70-B70) | O70: =IF(OR(I70=108000,I70=130000),"Starter",IF(I70=177000,"Growth","Premium")) -> Starter | P70: =TEXT(B70, "mmmm") -> June | Q70: ="Q"&ROUNDUP(MONTH(B70)/3,0) -> Q2 | R70: =IFERROR(VLOOKUP(TRIM(CLEAN(G70)),Sheet14!$A$2:$B$19,2,FALSE),"Not Mapped") -> West
A71: ="EOS"&TEXT(ROW()-1,"0000") -> EOS0070 | B71: 16/06/2025 | C71: FB | D71: =TRIM(CLEAN(SUBSTITUTE(C71,CHAR(160),""))) -> FB | E71: 𝙏𝙃𝙀 𝗩𝗔𝗚𝗛𝗘𝗟𝗔 𝗞𝗜𝗦𝗛𝗔𝗡 𝗢𝗙𝗙𝗜𝗖𝗜𝗔𝗟 | F71: Ahmedabad | G71: Gujarat | H71: Rejected | I71: 108000 | J71: 107069 | K71: =TRIM(Cleaned_CRM_Data!H71) -> Rejected | L71: =IFERROR(VLOOKUP(K71, Status_Mapping!A:B, 2,), "Not Found") -> Rejected | N71: =IF(M71="","",M71-B71) | O71: =IF(OR(I71=108000,I71=130000),"Starter",IF(I71=177000,"Growth","Premium")) -> Starter | P71: =TEXT(B71, "mmmm") -> June | Q71: ="Q"&ROUNDUP(MONTH(B71)/3,0) -> Q2 | R71: =IFERROR(VLOOKUP(TRIM(CLEAN(G71)),Sheet14!$A$2:$B$19,2,FALSE),"Not Mapped") -> West
A72: ="EOS"&TEXT(ROW()-1,"0000") -> EOS0071 | B72: 16/06/2025 | C72: FB | D72: =TRIM(CLEAN(SUBSTITUTE(C72,CHAR(160),""))) -> FB | E72: Nilesh ramavat | F72: damnagar | G72: Gujarat | H72: Rejected | I72: 108000 | J72: 107070 | K72: =TRIM(Cleaned_CRM_Data!H72) -> Rejected | L72: =IFERROR(VLOOKUP(K72, Status_Mapping!A:B, 2,), "Not Found") -> Rejected | N72: =IF(M72="","",M72-B72) | O72: =IF(OR(I72=108000,I72=130000),"Starter",IF(I72=177000,"Growth","Premium")) -> Starter | P72: =TEXT(B72, "mmmm") -> June | Q72: ="Q"&ROUNDUP(MONTH(B72)/3,0) -> Q2 | R72: =IFERROR(VLOOKUP(TRIM(CLEAN(G72)),Sheet14!$A$2:$B$19,2,FALSE),"Not Mapped") -> West
A73: ="EOS"&TEXT(ROW()-1,"0000") -> EOS0072 | B73: 16/06/2025 | C73: FB | D73: =TRIM(CLEAN(SUBSTITUTE(C73,CHAR(160),""))) -> FB | E73: Yunus | F73: Okha | G73: Gujarat | H73: Rejected | I73: 108000 | J73: 107071 | K73: =TRIM(Cleaned_CRM_Data!H73) -> Rejected | L73: =IFERROR(VLOOKUP(K73, Status_Mapping!A:B, 2,), "Not Found") -> Rejected | N73: =IF(M73="","",M73-B73) | O73: =IF(OR(I73=108000,I73=130000),"Starter",IF(I73=177000,"Growth","Premium")) -> Starter | P73: =TEXT(B73, "mmmm") -> June | Q73: ="Q"&ROUNDUP(MONTH(B73)/3,0) -> Q2 | R73: =IFERROR(VLOOKUP(TRIM(CLEAN(G73)),Sheet14!$A$2:$B$19,2,FALSE),"Not Mapped") -> West
A74: ="EOS"&TEXT(ROW()-1,"0000") -> EOS0073 | B74: 16/06/2025 | C74: FB | D74: =TRIM(CLEAN(SUBSTITUTE(C74,CHAR(160),""))) -> FB | E74: SMIT_____ox | F74: Unai | G74: Gujarat | H74: Rejected | I74: 108000 | J74: 107072 | K74: =TRIM(Cleaned_CRM_Data!H74) -> Rejected | L74: =IFERROR(VLOOKUP(K74, Status_Mapping!A:B, 2,), "Not Found") -> Rejected | N74: =IF(M74="","",M74-B74) | O74: =IF(OR(I74=108000,I74=130000),"Starter",IF(I74=177000,"Growth","Premium")) -> Starter | P74: =TEXT(B74, "mmmm") -> June | Q74: ="Q"&ROUNDUP(MONTH(B74)/3,0) -> Q2 | R74: =IFERROR(VLOOKUP(TRIM(CLEAN(G74)),Sheet14!$A$2:$B$19,2,FALSE),"Not Mapped") -> West
A75: ="EOS"&TEXT(ROW()-1,"0000") -> EOS0074 | B75: 16/06/2025 | C75: FB | D75: =TRIM(CLEAN(SUBSTITUTE(C75,CHAR(160),""))) -> FB | E75: Viju sankhat | F75: Mahuva | G75: Gujarat | H75: Rejected | I75: 130000 | J75: 107073 | K75: =TRIM(Cleaned_CRM_Data!H75) -> Rejected | L75: =IFERROR(VLOOKUP(K75, Status_Mapping!A:B, 2,), "Not Found") -> Rejected | N75: =IF(M75="","",M75-B75) | O75: =IF(OR(I75=108000,I75=130000),"Starter",IF(I75=177000,"Growth","Premium")) -> Starter | P75: =TEXT(B75, "mmmm") -> June | Q75: ="Q"&ROUNDUP(MONTH(B75)/3,0) -> Q2 | R75: =IFERROR(VLOOKUP(TRIM(CLEAN(G75)),Sheet14!$A$2:$B$19,2,FALSE),"Not Mapped") -> West
A76: ="EOS"&TEXT(ROW()-1,"0000") -> EOS0075 | B76: 16/06/2025 | C76: FB | D76: =TRIM(CLEAN(SUBSTITUTE(C76,CHAR(160),""))) -> FB | E76: Jadeja Harshdipsinhji | F76: Bhavnagar | G76: Gujarat | H76: Rejected | I76: 108000 | J76: 107074 | K76: =TRIM(Cleaned_CRM_Data!H76) -> Rejected | L76: =IFERROR(VLOOKUP(K76, Status_Mapping!A:B, 2,), "Not Found") -> Rejected | N76: =IF(M76="","",M76-B76) | O76: =IF(OR(I76=108000,I76=130000),"Starter",IF(I76=177000,"Growth","Premium")) -> Starter | P76: =TEXT(B76, "mmmm") -> June | Q76: ="Q"&ROUNDUP(MONTH(B76)/3,0) -> Q2 | R76: =IFERROR(VLOOKUP(TRIM(CLEAN(G76)),Sheet14!$A$2:$B$19,2,FALSE),"Not Mapped") -> West
A77: ="EOS"&TEXT(ROW()-1,"0000") -> EOS0076 | B77: 17/06/2025 | C77: FB | D77: =TRIM(CLEAN(SUBSTITUTE(C77,CHAR(160),""))) -> FB | E77: FeNeel Patel & Co. | F77: Surat | G77: Gujarat | H77: Rejected | I77: 130000 | J77: 107075 | K77: =TRIM(Cleaned_CRM_Data!H77) -> Rejected | L77: =IFERROR(VLOOKUP(K77, Status_Mapping!A:B, 2,), "Not Found") -> Rejected | N77: =IF(M77="","",M77-B77) | O77: =IF(OR(I77=108000,I77=130000),"Starter",IF(I77=177000,"Growth","Premium")) -> Starter | P77: =TEXT(B77, "mmmm") -> June | Q77: ="Q"&ROUNDUP(MONTH(B77)/3,0) -> Q2 | R77: =IFERROR(VLOOKUP(TRIM(CLEAN(G77)),Sheet14!$A$2:$B$19,2,FALSE),"Not Mapped") -> West
A78: ="EOS"&TEXT(ROW()-1,"0000") -> EOS0077 | B78: 17/06/2025 | C78: FB | D78: =TRIM(CLEAN(SUBSTITUTE(C78,CHAR(160),""))) -> FB | E78: Manish Kantibhai Patel | F78: Bharuch | G78: Gujarat | H78: Rejected | I78: 108000 | J78: 107076 | K78: =TRIM(Cleaned_CRM_Data!H78) -> Rejected | L78: =IFERROR(VLOOKUP(K78, Status_Mapping!A:B, 2,), "Not Found") -> Rejected | N78: =IF(M78="","",M78-B78) | O78: =IF(OR(I78=108000,I78=130000),"Starter",IF(I78=177000,"Growth","Premium")) -> Starter | P78: =TEXT(B78, "mmmm") -> June | Q78: ="Q"&ROUNDUP(MONTH(B78)/3,0) -> Q2 | R78: =IFERROR(VLOOKUP(TRIM(CLEAN(G78)),Sheet14!$A$2:$B$19,2,FALSE),"Not Mapped") -> West
A79: ="EOS"&TEXT(ROW()-1,"0000") -> EOS0078 | B79: 17/06/2025 | C79: FB | D79: =TRIM(CLEAN(SUBSTITUTE(C79,CHAR(160),""))) -> FB | E79: Akash Kapatel | F79: Anand | G79: Gujarat | H79: Rejected | I79: 108000 | J79: 107077 | K79: =TRIM(Cleaned_CRM_Data!H79) -> Rejected | L79: =IFERROR(VLOOKUP(K79, Status_Mapping!A:B, 2,), "Not Found") -> Rejected | N79: =IF(M79="","",M79-B79) | O79: =IF(OR(I79=108000,I79=130000),"Starter",IF(I79=177000,"Growth","Premium")) -> Starter | P79: =TEXT(B79, "mmmm") -> June | Q79: ="Q"&ROUNDUP(MONTH(B79)/3,0) -> Q2 | R79: =IFERROR(VLOOKUP(TRIM(CLEAN(G79)),Sheet14!$A$2:$B$19,2,FALSE),"Not Mapped") -> West
A80: ="EOS"&TEXT(ROW()-1,"0000") -> EOS0079 | B80: 17/06/2025 | C80: FB | D80: =TRIM(CLEAN(SUBSTITUTE(C80,CHAR(160),""))) -> FB | E80: Dhaval | F80: Valsad | G80: Gujarat | H80: Rejected | I80: 130000 | J80: 107078 | K80: =TRIM(Cleaned_CRM_Data!H80) -> Rejected | L80: =IFERROR(VLOOKUP(K80, Status_Mapping!A:B, 2,), "Not Found") -> Rejected | N80: =IF(M80="","",M80-B80) | O80: =IF(OR(I80=108000,I80=130000),"Starter",IF(I80=177000,"Growth","Premium")) -> Starter | P80: =TEXT(B80, "mmmm") -> June | Q80: ="Q"&ROUNDUP(MONTH(B80)/3,0) -> Q2 | R80: =IFERROR(VLOOKUP(TRIM(CLEAN(G80)),Sheet14!$A$2:$B$19,2,FALSE),"Not Mapped") -> West
A81: ="EOS"&TEXT(ROW()-1,"0000") -> EOS0080 | B81: 17/06/2025 | C81: FB | D81: =TRIM(CLEAN(SUBSTITUTE(C81,CHAR(160),""))) -> FB | E81: คʀຮhคd 𝐅ɑ𝐫ᵤⲕǐ | F81: Patan | G81: Gujarat | H81: Rejected | I81: 177000 | J81: 107079 | K81: =TRIM(Cleaned_CRM_Data!H81) -> Rejected | L81: =IFERROR(VLOOKUP(K81, Status_Mapping!A:B, 2,), "Not Found") -> Rejected | N81: =IF(M81="","",M81-B81) | O81: =IF(OR(I81=108000,I81=130000),"Starter",IF(I81=177000,"Growth","Premium")) -> Growth | P81: =TEXT(B81, "mmmm") -> June | Q81: ="Q"&ROUNDUP(MONTH(B81)/3,0) -> Q2 | R81: =IFERROR(VLOOKUP(TRIM(CLEAN(G81)),Sheet14!$A$2:$B$19,2,FALSE),"Not Mapped") -> West
... A83: ="EOS"&TEXT(ROW()-1,"0000") -> EOS0082 | B83: 18/06/2025 | C83: FB | D83: =TRIM(CLEAN(SUBSTITUTE(C83,CHAR(160),""))) -> FB | E83: Karan Khatri | F83: Surat | G83: Gujarat | H83: Rejected | I83: 130000 | J83: 107081 | K83: =TRIM(Cleaned_CRM_Data!H83) -> Rejected | L83: =IFERROR(VLOOKUP(K83, Status_Mapping!A:B, 2,), "Not Found") -> Rejected | N83: =IF(M83="","",M83-B83) | O83: =IF(OR(I83=108000,I83=130000),"Starter",IF(I83=177000,"Growth","Premium")) -> Starter | P83: =TEXT(B83, "mmmm") -> June | Q83: ="Q"&ROUNDUP(MONTH(B83)/3,0) -> Q2 | R83: =IFERROR(VLOOKUP(TRIM(CLEAN(G83)),Sheet14!$A$2:$B$19,2,FALSE),"Not Mapped") -> West
A84: ="EOS"&TEXT(ROW()-1,"0000") -> EOS0083 | B84: 18/06/2025 | C84: FB | D84: =TRIM(CLEAN(SUBSTITUTE(C84,CHAR(160),""))) -> FB | E84: Nikhil | F84: Rajkot | G84: Gujarat | H84: Rejected | I84: 130000 | J84: 107082 | K84: Deal | L84: =IFERROR(VLOOKUP(K84, Status_Mapping!A:B, 2,), "Not Found") -> Converted | N84: =IF(M84="","",M84-B84) | O84: =IF(OR(I84=108000,I84=130000),"Starter",IF(I84=177000,"Growth","Premium")) -> Starter | P84: =TEXT(B84, "mmmm") -> June | Q84: ="Q"&ROUNDUP(MONTH(B84)/3,0) -> Q2 | R84: =IFERROR(VLOOKUP(TRIM(CLEAN(G84)),Sheet14!$A$2:$B$19,2,FALSE),"Not Mapped") -> West
A85: ="EOS"&TEXT(ROW()-1,"0000") -> EOS0084 | B85: 18/06/2025 | C85: FB | D85: =TRIM(CLEAN(SUBSTITUTE(C85,CHAR(160),""))) -> FB | E85: Salim bhai | F85: Rapar | G85: Gujarat | H85: Rejected | I85: 108000 | J85: 107083 | K85: =TRIM(Cleaned_CRM_Data!H85) -> Rejected | L85: =IFERROR(VLOOKUP(K85, Status_Mapping!A:B, 2,), "Not Found") -> Rejected | N85: =IF(M85="","",M85-B85) | O85: =IF(OR(I85=108000,I85=130000),"Starter",IF(I85=177000,"Growth","Premium")) -> Starter | P85: =TEXT(B85, "mmmm") -> June | Q85: ="Q"&ROUNDUP(MONTH(B85)/3,0) -> Q2 | R85: =IFERROR(VLOOKUP(TRIM(CLEAN(G85)),Sheet14!$A$2:$B$19,2,FALSE),"Not Mapped") -> West
A86: ="EOS"&TEXT(ROW()-1,"0000") -> EOS0085 | B86: 18/06/2025 | C86: FB | D86: =TRIM(CLEAN(SUBSTITUTE(C86,CHAR(160),""))) -> FB | E86: yagnik | F86: Mehsana | G86: Gujarat | H86: Rejected | I86: 130000 | J86: 107084 | K86: =TRIM(Cleaned_CRM_Data!H86) -> Rejected | L86: =IFERROR(VLOOKUP(K86, Status_Mapping!A:B, 2,), "Not Found") -> Rejected | N86: =IF(M86="","",M86-B86) | O86: =IF(OR(I86=108000,I86=130000),"Starter",IF(I86=177000,"Growth","Premium")) -> Starter | P86: =TEXT(B86, "mmmm") -> June | Q86: ="Q"&ROUNDUP(MONTH(B86)/3,0) -> Q2 | R86: =IFERROR(VLOOKUP(TRIM(CLEAN(G86)),Sheet14!$A$2:$B$19,2,FALSE),"Not Mapped") -> West
A87: ="EOS"&TEXT(ROW()-1,"0000") -> EOS0086 | B87: 18/06/2025 | C87: FB | D87: =TRIM(CLEAN(SUBSTITUTE(C87,CHAR(160),""))) -> FB | E87: Raj | F87: Palghar | G87: Maharashtra | H87: Rejected | I87: 130000 | J87: 107085 | K87: =TRIM(Cleaned_CRM_Data!H87) -> Rejected | L87: =IFERROR(VLOOKUP(K87, Status_Mapping!A:B, 2,), "Not Found") -> Rejected | N87: =IF(M87="","",M87-B87) | O87: =IF(OR(I87=108000,I87=130000),"Starter",IF(I87=177000,"Growth","Premium")) -> Starter | P87: =TEXT(B87, "mmmm") -> June | Q87: ="Q"&ROUNDUP(MONTH(B87)/3,0) -> Q2 | R87: =IFERROR(VLOOKUP(TRIM(CLEAN(G87)),Sheet14!$A$2:$B$19,2,FALSE),"Not Mapped") -> West
A88: ="EOS"&TEXT(ROW()-1,"0000") -> EOS0087 | B88: 45815 | C88: FB | D88: =TRIM(CLEAN(SUBSTITUTE(C88,CHAR(160),""))) -> FB | E88: chaudhary nik | F88: Gandhinagar | G88: Gujarat | H88: Rejected | I88: 130000 | J88: 107086 | K88: =TRIM(Cleaned_CRM_Data!H88) -> Rejected | L88: =IFERROR(VLOOKUP(K88, Status_Mapping!A:B, 2,), "Not Found") -> Rejected | N88: =IF(M88="","",M88-B88) | O88: =IF(OR(I88=108000,I88=130000),"Starter",IF(I88=177000,"Growth","Premium")) -> Starter | P88: =TEXT(B88, "mmmm") -> June | Q88: ="Q"&ROUNDUP(MONTH(B88)/3,0) -> Q2 | R88: =IFERROR(VLOOKUP(TRIM(CLEAN(G88)),Sheet14!$A$2:$B$19,2,FALSE),"Not Mapped") -> West
A89: ="EOS"&TEXT(ROW()-1,"0000") -> EOS0088 | B89: 45815 | C89: FB | D89: =TRIM(CLEAN(SUBSTITUTE(C89,CHAR(160),""))) -> FB | E89: Kaushik | F89: Ahmedabad | G89: Gujarat | H89: Rejected | I89: 108000 | J89: 107087 | K89: =TRIM(Cleaned_CRM_Data!H89) -> Rejected | L89: =IFERROR(VLOOKUP(K89, Status_Mapping!A:B, 2,), "Not Found") -> Rejected | N89: =IF(M89="","",M89-B89) | O89: =IF(OR(I89=108000,I89=130000),"Starter",IF(I89=177000,"Growth","Premium")) -> Starter | P89: =TEXT(B89, "mmmm") -> June | Q89: ="Q"&ROUNDUP(MONTH(B89)/3,0) -> Q2 | R89: =IFERROR(VLOOKUP(TRIM(CLEAN(G89)),Sheet14!$A$2:$B$19,2,FALSE),"Not Mapped") -> West
A90: ="EOS"&TEXT(ROW()-1,"0000") -> EOS0089 | B90: 45815 | C90: FB | D90: =TRIM(CLEAN(SUBSTITUTE(C90,CHAR(160),""))) -> FB | E90: Parth Patel | F90: Surat | G90: Gujarat | H90: Rejected | I90: 108000 | J90: 107088 | K90: Deal | L90: =IFERROR(VLOOKUP(K90, Status_Mapping!A:B, 2,), "Not Found") -> Converted | N90: =IF(M90="","",M90-B90) | O90: =IF(OR(I90=108000,I90=130000),"Starter",IF(I90=177000,"Growth","Premium")) -> Starter | P90: =TEXT(B90, "mmmm") -> June | Q90: ="Q"&ROUNDUP(MONTH(B90)/3,0) -> Q2 | R90: =IFERROR(VLOOKUP(TRIM(CLEAN(G90)),Sheet14!$A$2:$B$19,2,FALSE),"Not Mapped") -> West
A91: ="EOS"&TEXT(ROW()-1,"0000") -> EOS0090 | B91: 45817 | C91: FB | D91: =TRIM(CLEAN(SUBSTITUTE(C91,CHAR(160),""))) -> FB | E91: RAJPUROHIT LOONSINGH | F91: Vadodara | G91: Gujarat | H91: Rejected | I91: 130000 | J91: 107089 | K91: =TRIM(Cleaned_CRM_Data!H91) -> Rejected | L91: =IFERROR(VLOOKUP(K91, Status_Mapping!A:B, 2,), "Not Found") -> Rejected | N91: =IF(M91="","",M91-B91) | O91: =IF(OR(I91=108000,I91=130000),"Starter",IF(I91=177000,"Growth","Premium")) -> Starter | P91: =TEXT(B91, "mmmm") -> June | Q91: ="Q"&ROUNDUP(MONTH(B91)/3,0) -> Q2 | R91: =IFERROR(VLOOKUP(TRIM(CLEAN(G91)),Sheet14!$A$2:$B$19,2,FALSE),"Not Mapped") -> West
A92: ="EOS"&TEXT(ROW()-1,"0000") -> EOS0091 | B92: 45819 | C92: FB | D92: =TRIM(CLEAN(SUBSTITUTE(C92,CHAR(160),""))) -> FB | E92: 0 | F92: Porbandar | G92: Gujarat | H92: Rejected | I92: 108000 | J92: 107090 | K92: =TRIM(Cleaned_CRM_Data!H92) -> Rejected | L92: =IFERROR(VLOOKUP(K92, Status_Mapping!A:B, 2,), "Not Found") -> Rejected | N92: =IF(M92="","",M92-B92) | O92: =IF(OR(I92=108000,I92=130000),"Starter",IF(I92=177000,"Growth","Premium")) -> Starter | P92: =TEXT(B92, "mmmm") -> June | Q92: ="Q"&ROUNDUP(MONTH(B92)/3,0) -> Q2 | R92: =IFERROR(VLOOKUP(TRIM(CLEAN(G92)),Sheet14!$A$2:$B$19,2,FALSE),"Not Mapped") -> West
A93: ="EOS"&TEXT(ROW()-1,"0000") -> EOS0092 | B93: 45819 | C93: FB | D93: =TRIM(CLEAN(SUBSTITUTE(C93,CHAR(160),""))) -> FB | E93: Vikram Rabari | F93: Vinchhiya | G93: Gujarat | H93: Rejected | I93: 130000 | J93: 107091 | K93: =TRIM(Cleaned_CRM_Data!H93) -> Rejected | L93: =IFERROR(VLOOKUP(K93, Status_Mapping!A:B, 2,), "Not Found") -> Rejected | N93: =IF(M93="","",M93-B93) | O93: =IF(OR(I93=108000,I93=130000),"Starter",IF(I93=177000,"Growth","Premium")) -> Starter | P93: =TEXT(B93, "mmmm") -> June | Q93: ="Q"&ROUNDUP(MONTH(B93)/3,0) -> Q2 | R93: =IFERROR(VLOOKUP(TRIM(CLEAN(G93)),Sheet14!$A$2:$B$19,2,FALSE),"Not Mapped") -> West
A94: ="EOS"&TEXT(ROW()-1,"0000") -> EOS0093 | B94: 45819 | C94: FB | D94: =TRIM(CLEAN(SUBSTITUTE(C94,CHAR(160),""))) -> FB | E94: Mr. Collection | F94: Vadodara | G94: Gujarat | H94: Rejected | I94: 130000 | J94: 107092 | K94: =TRIM(Cleaned_CRM_Data!H94) -> Rejected | L94: =IFERROR(VLOOKUP(K94, Status_Mapping!A:B, 2,), "Not Found") -> Rejected | N94: =IF(M94="","",M94-B94) | O94: =IF(OR(I94=108000,I94=130000),"Starter",IF(I94=177000,"Growth","Premium")) -> Starter | P94: =TEXT(B94, "mmmm") -> June | Q94: ="Q"&ROUNDUP(MONTH(B94)/3,0) -> Q2 | R94: =IFERROR(VLOOKUP(TRIM(CLEAN(G94)),Sheet14!$A$2:$B$19,2,FALSE),"Not Mapped") -> West
A95: ="EOS"&TEXT(ROW()-1,"0000") -> EOS0094 | B95: 45820 | C95: FB | D95: =TRIM(CLEAN(SUBSTITUTE(C95,CHAR(160),""))) -> FB | E95: ibrahim_shekha | F95: surat | G95: Gujarat | H95: Rejected | I95: 130000 | J95: 107093 | K95: =TRIM(Cleaned_CRM_Data!H95) -> Rejected | L95: =IFERROR(VLOOKUP(K95, Status_Mapping!A:B, 2,), "Not Found") -> Rejected | N95: =IF(M95="","",M95-B95) | O95: =IF(OR(I95=108000,I95=130000),"Starter",IF(I95=177000,"Growth","Premium")) -> Starter | P95: =TEXT(B95, "mmmm") -> June | Q95: ="Q"&ROUNDUP(MONTH(B95)/3,0) -> Q2 | R95: =IFERROR(VLOOKUP(TRIM(CLEAN(G95)),Sheet14!$A$2:$B$19,2,FALSE),"Not Mapped") -> West
A96: ="EOS"&TEXT(ROW()-1,"0000") -> EOS0095 | B96: 13/06/2025 | C96: FB | D96: =TRIM(CLEAN(SUBSTITUTE(C96,CHAR(160),""))) -> FB | E96: Sandhya Prajapati | F96: Ahmedabad | G96: Gujarat | H96: Rejected | I96: 108000 | J96: 107094 | K96: =TRIM(Cleaned_CRM_Data!H96) -> Rejected | L96: =IFERROR(VLOOKUP(K96, Status_Mapping!A:B, 2,), "Not Found") -> Rejected | N96: =IF(M96="","",M96-B96) | O96: =IF(OR(I96=108000,I96=130000),"Starter",IF(I96=177000,"Growth","Premium")) -> Starter | P96: =TEXT(B96, "mmmm") -> June | Q96: ="Q"&ROUNDUP(MONTH(B96)/3,0) -> Q2 | R96: =IFERROR(VLOOKUP(TRIM(CLEAN(G96)),Sheet14!$A$2:$B$19,2,FALSE),"Not Mapped") -> West
A97: ="EOS"&TEXT(ROW()-1,"0000") -> EOS0096 | B97: 13/06/2025 | C97: FB | D97: =TRIM(CLEAN(SUBSTITUTE(C97,CHAR(160),""))) -> FB | E97: Montu Rathod | F97: Jetpur | G97: Gujarat | H97: Rejected | I97: 130000 | J97: 107095 | K97: =TRIM(Cleaned_CRM_Data!H97) -> Rejected | L97: =IFERROR(VLOOKUP(K97, Status_Mapping!A:B, 2,), "Not Found") -> Rejected | N97: =IF(M97="","",M97-B97) | O97: =IF(OR(I97=108000,I97=130000),"Starter",IF(I97=177000,"Growth","Premium")) -> Starter | P97: =TEXT(B97, "mmmm") -> June | Q97: ="Q"&ROUNDUP(MONTH(B97)/3,0) -> Q2 | R97: =IFERROR(VLOOKUP(TRIM(CLEAN(G97)),Sheet14!$A$2:$B$19,2,FALSE),"Not Mapped") -> West
A98: ="EOS"&TEXT(ROW()-1,"0000") -> EOS0097 | B98: 14/06/2025 | C98: FB | D98: =TRIM(CLEAN(SUBSTITUTE(C98,CHAR(160),""))) -> FB | E98: Raeesh Shaikh | F98: Rajkot | G98: Gujarat | H98: Rejected | I98: 130000 | J98: 107096 | K98: =TRIM(Cleaned_CRM_Data!H98) -> Rejected | L98: =IFERROR(VLOOKUP(K98, Status_Mapping!A:B, 2,), "Not Found") -> Rejected | N98: =IF(M98="","",M98-B98) | O98: =IF(OR(I98=108000,I98=130000),"Starter",IF(I98=177000,"Growth","Premium")) -> Starter | P98: =TEXT(B98, "mmmm") -> June | Q98: ="Q"&ROUNDUP(MONTH(B98)/3,0) -> Q2 | R98: =IFERROR(VLOOKUP(TRIM(CLEAN(G98)),Sheet14!$A$2:$B$19,2,FALSE),"Not Mapped") -> West
A99: ="EOS"&TEXT(ROW()-1,"0000") -> EOS0098 | B99: 14/06/2025 | C99: FB | D99: =TRIM(CLEAN(SUBSTITUTE(C99,CHAR(160),""))) -> FB | E99: Jaydeep Devda | F99: Fatepura | G99: Gujarat | H99: Rejected | I99: 108000 | J99: 107097 | K99: =TRIM(Cleaned_CRM_Data!H99) -> Rejected | L99: =IFERROR(VLOOKUP(K99, Status_Mapping!A:B, 2,), "Not Found") -> Rejected | N99: =IF(M99="","",M99-B99) | O99: =IF(OR(I99=108000,I99=130000),"Starter",IF(I99=177000,"Growth","Premium")) -> Starter | P99: =TEXT(B99, "mmmm") -> June | Q99: ="Q"&ROUNDUP(MONTH(B99)/3,0) -> Q2 | R99: =IFERROR(VLOOKUP(TRIM(CLEAN(G99)),Sheet14!$A$2:$B$19,2,FALSE),"Not Mapped") -> West
A100: ="EOS"&TEXT(ROW()-1,"0000") -> EOS0099 | B100: 14/06/2025 | C100: FB | D100: =TRIM(CLEAN(SUBSTITUTE(C100,CHAR(160),""))) -> FB | E100: Sohil Barchha | F100: Rajkot | G100: Gujarat | H100: Rejected | I100: 130000 | J100: 107098 | K100: =TRIM(Cleaned_CRM_Data!H100) -> Rejected | L100: =IFERROR(VLOOKUP(K100, Status_Mapping!A:B, 2,), "Not Found") -> Rejected | N100: =IF(M100="","",M100-B100) | O100: =IF(OR(I100=108000,I100=130000),"Starter",IF(I100=177000,"Growth","Premium")) -> Starter | P100: =TEXT(B100, "mmmm") -> June | Q100: ="Q"&ROUNDUP(MONTH(B100)/3,0) -> Q2 | R100: =IFERROR(VLOOKUP(TRIM(CLEAN(G100)),Sheet14!$A$2:$B$19,2,FALSE),"Not Mapped") -> West
A101: ="EOS"&TEXT(ROW()-1,"0000") -> EOS0100 | B101: 16/06/2025 | C101: FB | D101: =TRIM(CLEAN(SUBSTITUTE(C101,CHAR(160),""))) -> FB | E101: Mihir P Machhi | F101: Rajpipla | G101: Gujarat | H101: Rejected | I101: 130000 | J101: 107099 | K101: =TRIM(Cleaned_CRM_Data!H101) -> Rejected | L101: =IFERROR(VLOOKUP(K101, Status_Mapping!A:B, 2,), "Not Found") -> Rejected | N101: =IF(M101="","",M101-B101) | O101: =IF(OR(I101=108000,I101=130000),"Starter",IF(I101=177000,"Growth","Premium")) -> Starter | P101: =TEXT(B101, "mmmm") -> June | Q101: ="Q"&ROUNDUP(MONTH(B101)/3,0) -> Q2 | R101: =IFERROR(VLOOKUP(TRIM(CLEAN(G101)),Sheet14!$A$2:$B$19,2,FALSE),"Not Mapped") -> West
A102: ="EOS"&TEXT(ROW()-1,"0000") -> EOS0101 | B102: 16/06/2025 | C102: FB | D102: =TRIM(CLEAN(SUBSTITUTE(C102,CHAR(160),""))) -> FB | E102: Timir Shah | F102: Bhuj | G102: Gujarat | H102: Rejected | I102: 130000 | J102: 107100 | K102: =TRIM(Cleaned_CRM_Data!H102) -> Rejected | L102: =IFERROR(VLOOKUP(K102, Status_Mapping!A:B, 2,), "Not Found") -> Rejected | N102: =IF(M102="","",M102-B102) | O102: =IF(OR(I102=108000,I102=130000),"Starter",IF(I102=177000,"Growth","Premium")) -> Starter | P102: =TEXT(B102, "mmmm") -> June | Q102: ="Q"&ROUNDUP(MONTH(B102)/3,0) -> Q2 | R102: =IFERROR(VLOOKUP(TRIM(CLEAN(G102)),Sheet14!$A$2:$B$19,2,FALSE),"Not Mapped") -> West
A103: ="EOS"&TEXT(ROW()-1,"0000") -> EOS0102 | B103: 16/06/2025 | C103: FB | D103: =TRIM(CLEAN(SUBSTITUTE(C103,CHAR(160),""))) -> FB | E103: Ahir Umesh Barad | F103: Rajkot | G103: Gujarat | H103: Rejected | I103: 108000 | J103: 107101 | K103: =TRIM(Cleaned_CRM_Data!H103) -> Rejected | L103: =IFERROR(VLOOKUP(K103, Status_Mapping!A:B, 2,), "Not Found") -> Rejected | N103: =IF(M103="","",M103-B103) | O103: =IF(OR(I103=108000,I103=130000),"Starter",IF(I103=177000,"Growth","Premium")) -> Starter | P103: =TEXT(B103, "mmmm") -> June | Q103: ="Q"&ROUNDUP(MONTH(B103)/3,0) -> Q2 | R103: =IFERROR(VLOOKUP(TRIM(CLEAN(G103)),Sheet14!$A$2:$B$19,2,FALSE),"Not Mapped") -> West
A104: ="EOS"&TEXT(ROW()-1,"0000") -> EOS0103 | B104: 18/06/2025 | C104: FB | D104: =TRIM(CLEAN(SUBSTITUTE(C104,CHAR(160),""))) -> FB | E104: નટખટ મારો કાનો | F104: Surat | G104: Gujarat | H104: Rejected | I104: 130000 | J104: 107102 | K104: =TRIM(Cleaned_CRM_Data!H104) -> Rejected | L104: =IFERROR(VLOOKUP(K104, Status_Mapping!A:B, 2,), "Not Found") -> Rejected | N104: =IF(M104="","",M104-B104) | O104: =IF(OR(I104=108000,I104=130000),"Starter",IF(I104=177000,"Growth","Premium")) -> Starter | P104: =TEXT(B104, "mmmm") -> June | Q104: ="Q"&ROUNDUP(MONTH(B104)/3,0) -> Q2 | R104: =IFERROR(VLOOKUP(TRIM(CLEAN(G104)),Sheet14!$A$2:$B$19,2,FALSE),"Not Mapped") -> West
A105: ="EOS"&TEXT(ROW()-1,"0000") -> EOS0104 | B105: 18/06/2025 | C105: FB | D105: =TRIM(CLEAN(SUBSTITUTE(C105,CHAR(160),""))) -> FB | E105: bhagirath Singh Rathore | F105: sankhara | G105: Rajasthan | H105: Rejected | I105: 108000 | J105: 107103 | K105: =TRIM(Cleaned_CRM_Data!H105) -> Rejected | L105: =IFERROR(VLOOKUP(K105, Status_Mapping!A:B, 2,), "Not Found") -> Rejected | N105: =IF(M105="","",M105-B105) | O105: =IF(OR(I105=108000,I105=130000),"Starter",IF(I105=177000,"Growth","Premium")) -> Starter | P105: =TEXT(B105, "mmmm") -> June | Q105: ="Q"&ROUNDUP(MONTH(B105)/3,0) -> Q2 | R105: =IFERROR(VLOOKUP(TRIM(CLEAN(G105)),Sheet14!$A$2:$B$19,2,FALSE),"Not Mapped") -> West
A106: ="EOS"&TEXT(ROW()-1,"0000") -> EOS0105 | B106: 18/06/2025 | C106: FB | D106: =TRIM(CLEAN(SUBSTITUTE(C106,CHAR(160),""))) -> FB | E106: Mihir | F106: Porbandar | G106: Gujarat | H106: Rejected | I106: 130000 | J106: 107104 | K106: =TRIM(Cleaned_CRM_Data!H106) -> Rejected | L106: =IFERROR(VLOOKUP(K106, Status_Mapping!A:B, 2,), "Not Found") -> Rejected | N106: =IF(M106="","",M106-B106) | O106: =IF(OR(I106=108000,I106=130000),"Starter",IF(I106=177000,"Growth","Premium")) -> Starter | P106: =TEXT(B106, "mmmm") -> June | Q106: ="Q"&ROUNDUP(MONTH(B106)/3,0) -> Q2 | R106: =IFERROR(VLOOKUP(TRIM(CLEAN(G106)),Sheet14!$A$2:$B$19,2,FALSE),"Not Mapped") -> West
A107: ="EOS"&TEXT(ROW()-1,"0000") -> EOS0106 | B107: 18/06/2025 | C107: FB | D107: =TRIM(CLEAN(SUBSTITUTE(C107,CHAR(160),""))) -> FB | E107: Amit Patel | F107: Narsinghpur | G107: Madhya Pradesh | H107: Rejected | I107: 108000 | J107: 107105 | K107: =TRIM(Cleaned_CRM_Data!H107) -> Rejected | L107: =IFERROR(VLOOKUP(K107, Status_Mapping!A:B, 2,), "Not Found") -> Rejected | N107: =IF(M107="","",M107-B107) | O107: =IF(OR(I107=108000,I107=130000),"Starter",IF(I107=177000,"Growth","Premium")) -> Starter | P107: =TEXT(B107, "mmmm") -> June | Q107: ="Q"&ROUNDUP(MONTH(B107)/3,0) -> Q2 | R107: =IFERROR(VLOOKUP(TRIM(CLEAN(G107)),Sheet14!$A$2:$B$19,2,FALSE),"Not Mapped") -> Central
... A122: ="EOS"&TEXT(ROW()-1,"0000") -> EOS0121 | B122: 18/06/2025 | C122: FB | D122: =TRIM(CLEAN(SUBSTITUTE(C122,CHAR(160),""))) -> FB | E122: Meet Patadiya | F122: Ahmedabad | G122: Gujarat | H122: Rejected | I122: 108000 | J122: 107120 | K122: =TRIM(Cleaned_CRM_Data!H122) -> Rejected | L122: =IFERROR(VLOOKUP(K122, Status_Mapping!A:B, 2,), "Not Found") -> Rejected | N122: =IF(M122="","",M122-B122) | O122: =IF(OR(I122=108000,I122=130000),"Starter",IF(I122=177000,"Growth","Premium")) -> Starter | P122: =TEXT(B122, "mmmm") -> June | Q122: ="Q"&ROUNDUP(MONTH(B122)/3,0) -> Q2 | R122: =IFERROR(VLOOKUP(TRIM(CLEAN(G122)),Sheet14!$A$2:$B$19,2,FALSE),"Not Mapped") -> West
A123: ="EOS"&TEXT(ROW()-1,"0000") -> EOS0122 | B123: 18/06/2025 | C123: FB | D123: =TRIM(CLEAN(SUBSTITUTE(C123,CHAR(160),""))) -> FB | E123: chauhan jayant | F123: Rajkot | G123: Gujarat | H123: Rejected | I123: 130000 | J123: 107121 | K123: Deal | L123: =IFERROR(VLOOKUP(K123, Status_Mapping!A:B, 2,), "Not Found") -> Converted | N123: =IF(M123="","",M123-B123) | O123: =IF(OR(I123=108000,I123=130000),"Starter",IF(I123=177000,"Growth","Premium")) -> Starter | P123: =TEXT(B123, "mmmm") -> June | Q123: ="Q"&ROUNDUP(MONTH(B123)/3,0) -> Q2 | R123: =IFERROR(VLOOKUP(TRIM(CLEAN(G123)),Sheet14!$A$2:$B$19,2,FALSE),"Not Mapped") -> West
A124: ="EOS"&TEXT(ROW()-1,"0000") -> EOS0123 | B124: 18/06/2025 | C124: FB | D124: =TRIM(CLEAN(SUBSTITUTE(C124,CHAR(160),""))) -> FB | E124: Akash Aggarwal | F124: Ghaziabad | G124: Uttar Pradesh | H124: Rejected | I124: 108000 | J124: 107122 | K124: =TRIM(Cleaned_CRM_Data!H124) -> Rejected | L124: =IFERROR(VLOOKUP(K124, Status_Mapping!A:B, 2,), "Not Found") -> Rejected | N124: =IF(M124="","",M124-B124) | O124: =IF(OR(I124=108000,I124=130000),"Starter",IF(I124=177000,"Growth","Premium")) -> Starter | P124: =TEXT(B124, "mmmm") -> June | Q124: ="Q"&ROUNDUP(MONTH(B124)/3,0) -> Q2 | R124: =IFERROR(VLOOKUP(TRIM(CLEAN(G124)),Sheet14!$A$2:$B$19,2,FALSE),"Not Mapped") -> North
A125: ="EOS"&TEXT(ROW()-1,"0000") -> EOS0124 | B125: 18/06/2025 | C125: FB | D125: =TRIM(CLEAN(SUBSTITUTE(C125,CHAR(160),""))) -> FB | E125: Arshad Khan | F125: Baikunthpur | G125: Chattisgarh | H125: Rejected | I125: 108000 | J125: 107123 | K125: =TRIM(Cleaned_CRM_Data!H125) -> Rejected | L125: =IFERROR(VLOOKUP(K125, Status_Mapping!A:B, 2,), "Not Found") -> Rejected | N125: =IF(M125="","",M125-B125) | O125: =IF(OR(I125=108000,I125=130000),"Starter",IF(I125=177000,"Growth","Premium")) -> Starter | P125: =TEXT(B125, "mmmm") -> June | Q125: ="Q"&ROUNDUP(MONTH(B125)/3,0) -> Q2 | R125: =IFERROR(VLOOKUP(TRIM(CLEAN(G125)),Sheet14!$A$2:$B$19,2,FALSE),"Not Mapped") -> Central
A126: ="EOS"&TEXT(ROW()-1,"0000") -> EOS0125 | B126: 18/06/2025 | C126: FB | D126: =TRIM(CLEAN(SUBSTITUTE(C126,CHAR(160),""))) -> FB | E126: Samad | F126: Kanpur | G126: Uttar Pradesh | H126: Deal | I126: 130000 | J126: 107124 | K126: =TRIM(Cleaned_CRM_Data!H126) -> Deal | L126: =IFERROR(VLOOKUP(K126, Status_Mapping!A:B, 2,), "Not Found") -> Converted | M126: 45836 | N126: =IF(M126="","",M126-B126) -> 10 | O126: =IF(OR(I126=108000,I126=130000),"Starter",IF(I126=177000,"Growth","Premium")) -> Starter | P126: =TEXT(B126, "mmmm") -> June | Q126: ="Q"&ROUNDUP(MONTH(B126)/3,0) -> Q2 | R126: =IFERROR(VLOOKUP(TRIM(CLEAN(G126)),Sheet14!$A$2:$B$19,2,FALSE),"Not Mapped") -> North
A127: ="EOS"&TEXT(ROW()-1,"0000") -> EOS0126 | B127: 18/06/2025 | C127: FB | D127: =TRIM(CLEAN(SUBSTITUTE(C127,CHAR(160),""))) -> FB | E127: Avakesh Vaghela | F127: Gandhinagar | G127: Gujarat | H127: Rejected | I127: 108000 | J127: 107125 | K127: =TRIM(Cleaned_CRM_Data!H127) -> Rejected | L127: =IFERROR(VLOOKUP(K127, Status_Mapping!A:B, 2,), "Not Found") -> Rejected | N127: =IF(M127="","",M127-B127) | O127: =IF(OR(I127=108000,I127=130000),"Starter",IF(I127=177000,"Growth","Premium")) -> Starter | P127: =TEXT(B127, "mmmm") -> June | Q127: ="Q"&ROUNDUP(MONTH(B127)/3,0) -> Q2 | R127: =IFERROR(VLOOKUP(TRIM(CLEAN(G127)),Sheet14!$A$2:$B$19,2,FALSE),"Not Mapped") -> West
A128: ="EOS"&TEXT(ROW()-1,"0000") -> EOS0127 | B128: 19/06/2025 | C128: FB | D128: =TRIM(CLEAN(SUBSTITUTE(C128,CHAR(160),""))) -> FB | E128: Ranjitsinh Thakor | F128: Vadnagar | G128: Gujarat | H128: Rejected | I128: 108000 | J128: 107126 | K128: =TRIM(Cleaned_CRM_Data!H128) -> Rejected | L128: =IFERROR(VLOOKUP(K128, Status_Mapping!A:B, 2,), "Not Found") -> Rejected | N128: =IF(M128="","",M128-B128) | O128: =IF(OR(I128=108000,I128=130000),"Starter",IF(I128=177000,"Growth","Premium")) -> Starter | P128: =TEXT(B128, "mmmm") -> June | Q128: ="Q"&ROUNDUP(MONTH(B128)/3,0) -> Q2 | R128: =IFERROR(VLOOKUP(TRIM(CLEAN(G128)),Sheet14!$A$2:$B$19,2,FALSE),"Not Mapped") -> West
A129: ="EOS"&TEXT(ROW()-1,"0000") -> EOS0128 | B129: 19/06/2025 | C129: FB | D129: =TRIM(CLEAN(SUBSTITUTE(C129,CHAR(160),""))) -> FB | E129: Pravinsinh | F129: Chadasna | G129: Gujarat | H129: Rejected | I129: 130000 | J129: 107127 | K129: =TRIM(Cleaned_CRM_Data!H129) -> Rejected | L129: =IFERROR(VLOOKUP(K129, Status_Mapping!A:B, 2,), "Not Found") -> Rejected | N129: =IF(M129="","",M129-B129) | O129: =IF(OR(I129=108000,I129=130000),"Starter",IF(I129=177000,"Growth","Premium")) -> Starter | P129: =TEXT(B129, "mmmm") -> June | Q129: ="Q"&ROUNDUP(MONTH(B129)/3,0) -> Q2 | R129: =IFERROR(VLOOKUP(TRIM(CLEAN(G129)),Sheet14!$A$2:$B$19,2,FALSE),"Not Mapped") -> West
A130: ="EOS"&TEXT(ROW()-1,"0000") -> EOS0129 | B130: 19/06/2025 | C130: FB | D130: =TRIM(CLEAN(SUBSTITUTE(C130,CHAR(160),""))) -> FB | E130: Rajesh | F130: Bhavnagar | G130: Gujarat | H130: Rejected | I130: 108000 | J130: 107128 | K130: =TRIM(Cleaned_CRM_Data!H130) -> Rejected | L130: =IFERROR(VLOOKUP(K130, Status_Mapping!A:B, 2,), "Not Found") -> Rejected | N130: =IF(M130="","",M130-B130) | O130: =IF(OR(I130=108000,I130=130000),"Starter",IF(I130=177000,"Growth","Premium")) -> Starter | P130: =TEXT(B130, "mmmm") -> June | Q130: ="Q"&ROUNDUP(MONTH(B130)/3,0) -> Q2 | R130: =IFERROR(VLOOKUP(TRIM(CLEAN(G130)),Sheet14!$A$2:$B$19,2,FALSE),"Not Mapped") -> West
...

Sheet KPI_Databse
A1: Total Leads | B1: ='Month Wise analysis'!B17 -> 1778
A2: Converted Leads | B2: =Sheet4!B4 -> 45
A3: Conversion rate | B3: =B2/B1 -> 0.025309336
A4: Revenue generated | B4: =Sheet4!C4 -> 6198000
A5: Pipeline value | B5: =Sheet4!C5 -> 69576000
A6: Lost opportunity | B6: =Sheet4!C7 -> 119264000
A7: Avg Closure Days | B7: ='Sales Cycle Analysis'!B7 -> 13

Sheet Sales Cycle Analysis
A1: Standard Status | B1: Converted
A3: Pacakge Category | B3: Average of Days To Closure
A4: Growth | B4: 6.5
A5: Premium | B5: 11
A6: Starter | B6: 14.307692
A7: Grand Total | B7: 13
A11: Standard Status | B11: Converted
A13: Zone | B13: Average of Days To Closure
A14: Central | B14: 7
A15: East | B15: 9
A16: North | B16: 10
A17: West | B17: 13.928571
A18: Grand Total | B18: 13
A24: Standard Status | B24: Converted
A26: Zone | B26: Total Revenue Generated
A27: Central | B27: 354000
A28: East | B28: 108000
A29: North | B29: 390000
A30: West | B30: 5346000
A31: Grand Total | B31: 6198000

Sheet Sheet4
A3: Standard Status | B3: Count of Lead ID | C3: Sum of Franchise Package Amount
A4: Converted | B4: 45 | C4: 6198000
A5: Follow Up | B5: 541 | C5: 69576000
A6: Not Found | B6: 268 | C6: 34561000
A7: Rejected | B7: 924 | C7: 119264000
A8: (blank)
A9: Grand Total | B9: 1778 | C9: 229599000

Sheet Month Wise analysis
E1: Standard Status | F1: Converted
A3: Lead Month | B3: Total Leads | E3: Lead Month | F3: Converted Leads
A4: January | B4: 150 | E4: March | F4: 3
A5: February | B5: 123 | E5: April | F5: 3
A6: March | B6: 60 | E6: May | F6: 1
A7: April | B7: 135 | E7: June | F7: 13
A8: May | B8: 134 | E8: July | F8: 8
A9: June | B9: 199 | E9: August | F9: 3
A10: July | B10: 284 | E10: September | F10: 4
A11: August | B11: 194 | E11: October | F11: 9
A12: September | B12: 177 | E12: November | F12: 1
A13: October | B13: 116 | E13: Grand Total | F13: 45
A14: November | B14: 73 | G14: Monthly Conversion Rate
A15: December | B15: 133 | E15: January | F15: 0 | G15: 0
A16: (blank) | E16: February | F16: 0 | G16: 0
A17: Grand Total | B17: 1778 | E17: March | F17: 3 | G17: =F17/B6 -> 0.05
E18: April | F18: 3 | G18: =F18/B7 -> 0.022222222
E19: May | F19: 1 | G19: =F19/B8 -> 0.0074626866
E20: June | F20: 12 | G20: =F20/B9 -> 0.060301508
E21: July | F21: 8 | G21: =F21/B10 -> 0.028169014
E22: August | F22: 3 | G22: =F22/B11 -> 0.015463918
E23: September | F23: 2 | G23: =F23/B12 -> 0.011299435
E24: October | F24: 0 | G24: 0
E25: November | F25: 1 | G25: =F25/B14 -> 0.01369863
E26: December | F26: 0 | G26: 0

Sheet Monthly closed deals
A1: Standard Status | B1: Converted
A3: Lead Month | B3: Count of Lead ID
A4: March | B4: 3
A5: April | B5: 3
A6: May | B6: 1
A7: June | B7: 13
A8: July | B8: 8
A9: August | B9: 3
A10: September | B10: 4
A11: October | B11: 9
A12: November | B12: 1
A13: Grand Total | B13: 45

Sheet Total Pipeline Value
A3: Standard Status | B3: Sum of Franchise Package Amount
A4: Converted | B4: 6198000
A5: Follow Up | B5: 69576000
A6: Not Found | B6: 34561000
A7: Rejected | B7: 119264000
A8: (blank)
A9: Grand Total | B9: 229599000

Sheet Franchise performance
A1: Standard Status | B1: Converted
A3: Pacakge Category | B3: Sum of Franchise Package Amount
A4: Growth | B4: 708000
A5: Premium | B5: 816000
A6: Starter | B6: 4674000
A7: Grand Total | B7: 6198000
A11: Standard Status | B11: Converted
A13: Pacakge Category | B13: Total Leads | C13: Sum of Franchise Package Amount | D13: Conversion rate
A14: Growth | B14: 4 | C14: 708000 | D14: =B14/B4 -> 5.6497175e-06
A15: Premium | B15: 2 | C15: 816000 | D15: =B15/B5 -> 2.4509804e-06
A16: Starter | B16: 39 | C16: 4674000 | D16: =B16/B6 -> 8.3440308e-06
A17: Grand Total | B17: 45 | C17: 6198000

Sheet Zone Wise Analysis
A1: Standard Status | B1: (All)
A3: Zone | B3: Lead | C3: Count of Franchise Package Amount
A4: Central | B4: 30 | C4: 30
A5: East | B5: 49 | C5: 49
A6: North | B6: 112 | C6: 112
A7: Not Mapped | B7: 18 | C7: 18
A8: West | B8: 1569 | C8: 1569
A9: (blank)
A10: Grand Total | B10: 1778 | C10: 1778
A11: Standard Status | B11: Converted
A13: Zone | B13: Lead | C13: Potential revenue | D13: Zone Conversion Share | E13: Zone Conversion rate
A14: Central | B14: 2 | C14: 354000 | D14: =B14/B18 -> 0.044444444 | E14: =B14/B4 -> 0.066666667
A15: East | B15: 1 | C15: 108000 | D15: =B15/B18 -> 0.022222222 | E15: =B15/B5 -> 0.020408163
A16: North | B16: 3 | C16: 390000 | D16: =B16/B18 -> 0.066666667 | E16: =B16/B6 -> 0.026785714
A17: West | B17: 39 | C17: 5346000 | D17: =B17/B18 -> 0.86666667 | E17: =B17/B8 -> 0.024856597
A18: Grand Total | B18: 45 | C18: 6198000
A23: 2
A24: 1
A25: 3
A26: 27

Sheet Sheet5
C2: Total Leads | E2: Conversion Rate
C3: =COUNTA(Cleaned_CRM_Data!A2:A1779) -> 1778 | E3: =C6/C3 -> 0.025309336
C5: Converted Leads | E5: Total Converted revenue
C6: =COUNTIF(Cleaned_CRM_Data!L:L,"Converted") -> 45 | E6: =SUMIF(Cleaned_CRM_Data!L:L,"Converted",Cleaned_CRM_Data!I:I) -> 6198000
E8: Pipeline Value
E9: =SUMIF(Cleaned_CRM_Data!L:L, "Follow up",Cleaned_CRM_Data!I:I) -> 69576000
E11: Lost Opportunity Value
C12: ` | E12: =SUMIF(Cleaned_CRM_Data!L:L, "Rejected", Cleaned_CRM_Data!I:I) -> 119264000

Sheet Status_Mapping
A1: Raw_Status | B1: Standard_Status
A2: Deal | B2: Converted
A3: Deal Done | B3: Converted
A4: Follow up | B4: Follow Up
A5: Ringing | B5: Follow Up
A6: Rejected | B6: Rejected
E10: =F754 -> 0
